{
  "ignited": { "name": "点燃", "description": "你被点燃了. " },
  "chilled": { "name": "冰缓", "description": "你被冰缓一段时间. " },
  "frozen": { "name": "冰冻", "description": "你被冰冻了. " },
  "shocked": { "name": "感电", "description": "你受到至多 50% 额外伤害. " },
  "sprinting": { "name": "疾跑", "description": "增加移动速度. " },
  "flask_effect_life": { "name": "生命回复", "description": "" },
  "grace_period": { "name": "恩典", "description": "你不会受到伤害. " },
  "god_mode": { "name": "无敌", "description": "你不会受到任何伤害. " },
  "experience": { "name": "经验增加", "description": "30 秒内增加经验值. " },
  "flask_effect_mana": { "name": "魔力回复", "description": "" },
  "poison": { "name": "中毒", "description": "你受到混沌伤害. " },
  "blood_rage": {
    "name": "鲜血狂怒",
    "description":
      "根据生命和能量护盾的多少受到持续的物理伤害, 同时增加生命偷取和攻击速度, 击败敌人会刷新技能持续时间并获得一个狂怒能量球. "
  },
  "righteous_fire": {
    "name": "正义之火",
    "description": "点燃自己并对周围的敌人造成伤害, 增加法术伤害. "
  },
  "righteous_fire_aura": {
    "name": "正义之火",
    "description": "附近正在使用正义之火的敌人对你造成燃烧伤害. "
  },
  "demon_righteous_fire": {
    "name": "邪恶之火",
    "description": "点燃自己并对周围的敌人造成伤害, 增加法术伤害. "
  },
  "demon_righteous_fire_aura": {
    "name": "邪恶之火",
    "description": "附近正在使用邪恶之火的敌人对你造成燃烧伤害. "
  },
  "avatar_righteous_fire": {
    "name": "正义之火",
    "description": "点燃自己并对周围的敌人造成燃烧伤害, 同时法术伤害增加. "
  },
  "avatar_righteous_fire_aura": {
    "name": "正义之火",
    "description": "附近正在使用正义之火的敌人对你造成燃烧伤害. "
  },
  "invisible_fire_aura": { "name": "", "description": "" },
  "invisible_fire_debuff": {
    "name": "持续苦痛",
    "description": "你被持续苦痛影响，正在受到燃烧伤害。"
  },
  "invisible_holy_fire_debuff": {
    "name": "神圣之光",
    "description": "你正持续受到附近神圣之光的燃烧伤害. "
  },
  "invisible_holy_fire_elder_debuff": {
    "name": "神圣之光",
    "description": "你被神圣之光影响，正在受到燃烧伤害。"
  },
  "invisible_kitava_fire_debuff": {
    "name": "不洁之光",
    "description": "你正持续受到附近不洁之光的燃烧伤害. "
  },
  "ion_beam_debuff": {
    "name": "电光束",
    "description": "你正持续受到附近电光束的闪电伤害. "
  },
  "frost_ion_beam_debuff": {
    "name": "电光寒霜",
    "description": "你正持续受到附近电光寒霜的冰霜伤害. "
  },
  "doedre_invisible_chaos_debuff": {
    "name": "污水毒素",
    "description": "你正在受到持续的混沌伤害."
  },
  "fire_weapon": {
    "name": "烈焰武器",
    "description": "你的武器造成额外火焰伤害. "
  },
  "frenzy_charge": {
    "name": "狂怒能量球",
    "description": "每个狂怒能量球将提供额外总伤害, 增加攻击速度与施法速度. "
  },
  "endurance_charge": {
    "name": "耐力能量球",
    "description": "每个耐力能量球将提供额外物理伤害减免. "
  },
  "power_charge": {
    "name": "暴击能量球",
    "description": "每个暴击能量球将增加暴击率. "
  },
  "spirit_charge": {
    "name": "精神能量球",
    "description": "需要使用特定技能。"
  },
  "siphoning_charge": { "name": "Siphoning Charges", "description": "" },
  "void_arrow": { "name": "Void Arrows", "description": "" },
  "hillock_buff": { "name": "残酷攻击", "description": "狂热的挥动着武器. " },
  "mana_leech": { "name": "魔力偷取", "description": "你正在偷取魔力. " },
  "life_leech": { "name": "生命偷取", "description": "你正在偷取生命. " },
  "energy_shield_leech": {
    "name": "能量护盾偷取",
    "description": "你正在偷取生命转化为能量护盾. "
  },
  "players_increased": {
    "name": "更多的玩家",
    "description": "更多玩家加入游戏. "
  },
  "flask_bonus_armour": {
    "name": "增加护甲",
    "description": "在药剂发挥作用时增加护甲值. "
  },
  "flask_bonus_evasion": {
    "name": "增加闪避",
    "description": "在药剂发挥作用时增加闪避值. "
  },
  "flask_bonus_energy_shield": {
    "name": "增加能量护盾",
    "description": "在药剂发挥作用时增加能量护盾上限. "
  },
  "flask_bonus_movement_speed": {
    "name": "增加移动速度",
    "description": "在药剂发挥作用时增加你的移动速度. "
  },
  "flask_bonus_stun_recovery": {
    "name": "提升晕眩回复",
    "description": "在药剂发挥作用时缩短你的晕眩回复时间. "
  },
  "flask_bonus_resistances": {
    "name": "增加抗性",
    "description": "在药剂发挥作用时增加你的抗性. "
  },
  "flask_bonus_life_leech": {
    "name": "增加生命偷取",
    "description": "在药剂发挥作用时获得生命偷取效果. "
  },
  "flask_bonus_mana_leech": {
    "name": "增加魔力偷取",
    "description": "在药剂发挥作用时获得魔力偷取效果. "
  },
  "flask_bonus_knockback": {
    "name": "增加击退",
    "description": "在药剂发挥作用时攻击附加击退敌人效果. "
  },
  "flask_bonus_global_knockback": {
    "name": "增加击退",
    "description": "在药剂发挥作用时你能击退敌人. "
  },
  "flask_bonus_prevents_death": {
    "name": "死亡免疫",
    "description": "在药剂发挥作用时你不会死亡. "
  },
  "flask_bonus_chill_and_freeze_immunity": {
    "name": "冰冻与冰缓免疫",
    "description": "在药剂发挥作用时免疫被冰冻与冰缓. "
  },
  "flask_bonus_ignite_immunity": {
    "name": "点燃免疫",
    "description": "在药剂发挥作用时免疫被点燃. "
  },
  "flask_bonus_shock_immunity": {
    "name": "感电免疫",
    "description": "在药剂发挥作用时免疫被感电. "
  },
  "flask_bonus_bleeding_immunity": {
    "name": "流血免疫",
    "description": "在药剂发挥作用时免疫流血. "
  },
  "flask_bonus_curse_immunity": {
    "name": "诅咒免疫",
    "description": "在药剂发挥作用时免疫诅咒. "
  },
  "spectre_buff": { "name": "特别", "description": "" },
  "infernal_blow_hit": { "name": "被炼狱之击击中", "description": "" },
  "viper_strike_orb": {
    "name": "被毒蛇打击击中",
    "description": "你受到毒蛇打击而中毒了. "
  },
  "phase_run": {
    "name": "相位奔驰",
    "description":
      "你的移动速度增加, 可以穿越敌人. 发动攻击会提前结束增益, 但该次攻击会造成额外伤害. "
  },
  "monster_magic_effect_buff": { "name": "", "description": "" },
  "monster_rare_effect_buff": { "name": "", "description": "" },
  "fuse_arrow_orb": { "name": "被爆炸箭矢击中", "description": "你要爆炸了. " },
  "curse_temporal_chains": {
    "name": "时空锁链",
    "description": "你被诅咒了, 时间的流动在你身上变得更缓慢. "
  },
  "curse_elemental_weakness": {
    "name": "元素要害",
    "description": "你被诅咒了, 将会受到更多火焰, 冰霜, 闪电伤害. "
  },
  "curse_fire_weakness": {
    "name": "易燃",
    "description": "你被诅咒了, 将会受到更多火焰伤害并且更容易被点燃. "
  },
  "curse_cold_weakness": {
    "name": "冻伤",
    "description": "你被诅咒了, 将会受到更多冰霜伤害并且更容易被冰冻. "
  },
  "curse_lightning_weakness": {
    "name": "导电",
    "description": "你被诅咒了, 将会受到更多闪电伤害并且更容易被感电. "
  },
  "curse_warlords_mark": {
    "name": "督军印记",
    "description":
      "你被诅咒了, 将更容易被眩晕且晕眩更久, 敌人击中你时获得生命与魔力偷取, 你被击败时可能为其提供耐力球. "
  },
  "curse_punishment": {
    "name": "惩戒",
    "description":
      "你被诅咒了, 你造成物理攻击的同时也会受到一定比例的物理伤害. "
  },
  "curse_enfeeble": {
    "name": "衰弱",
    "description": "你被诅咒了, 你攻击力降低, 更难命中敌人, 更不容易暴击"
  },
  "curse_assassins_mark": {
    "name": "暗影印记",
    "description":
      "你被诅咒了, 将会更容易被暴击, 受到更多暴击伤害, 被击败时为敌人回复生命与魔力并可能为其提供暴击球. "
  },
  "curse_projectile_weakness": {
    "name": "投射物要害",
    "description": "keleton Warrior"
  },
  "curse_vulnerability": {
    "name": "脆弱",
    "description":
      "你被诅咒了, 你将受到更多的物理伤害, 你受到的攻击有机会造成你瘫痪或流血. "
  },
  "curse_poachers_mark": {
    "name": "盗猎者印记",
    "description":
      "你被诅咒了, 你的闪避值降低, 敌人击中你时获得生命与魔力, 被击败时为敌人回复额外药剂充能并可能为其提供狂怒球. "
  },
  "curse_newpunishment": {
    "name": "新惩戒",
    "description":
      "你被诅咒了, 你的近战攻击给予敌人一个增益效果, 使它们造成更多进战伤害和攻击速度. "
  },
  "CarlsTestCheat": { "name": "平衡", "description": "测试" },
  "monster_aura_physical_thorns": {
    "name": "物理反射光环",
    "description": "周围友军反射物理伤害"
  },
  "monster_aura_elemental_thorns": {
    "name": "元素反射光环",
    "description": "周围友军反射火焰, 冰霜, 闪电伤害"
  },
  "monster_physical_thorns": {
    "name": "物理反射",
    "description": "反射物理伤害"
  },
  "monster_elemental_thorns": {
    "name": "元素反射",
    "description": "反射火焰, 冰霜, 闪电伤害"
  },
  "monster_aura_medium_physical_damage": {
    "name": "物理增伤光环",
    "description": "周围友军增加物理伤害"
  },
  "monster_aura_large_physical_damage": {
    "name": "强化物理增伤光环",
    "description": "周围友军大幅增加物理伤害"
  },
  "monster_aura_speed": {
    "name": "速度光环",
    "description": "周围友军增加攻击与移动速度"
  },
  "monster_aura_life_regen": {
    "name": "生命回复光环",
    "description": "周围友军增加每秒生命回复"
  },
  "monster_aura_resists": {
    "name": "抗性光环",
    "description": "周围友军增加元素抗性"
  },
  "monster_aura_energy_shield": {
    "name": "护盾光环",
    "description": "周围友军获得能量护盾"
  },
  "monster_aura_energy_shield_bubble": {
    "name": "护盾光环",
    "description": "周围友军获得能量护盾"
  },
  "monster_aura_accuracy_and_crits": {
    "name": "精准暴击光环",
    "description": "周围友军增加命中与暴击几率"
  },
  "monster_aura_pus_puke_degen": {
    "name": "混沌伤害光环",
    "description": "敌人持续受到混沌伤害"
  },
  "monster_aura_chaos_degen": {
    "name": "混沌伤害光环",
    "description": "敌人持续受到混沌伤害"
  },
  "monster_aura_physical_degen": {
    "name": "物理伤害光环",
    "description": "敌人持续受到物理伤害"
  },
  "monster_aura_lightning_degen": {
    "name": "混沌伤害光环",
    "description": "敌人受到持续闪电伤害"
  },
  "monster_aura_elemental_damage": {
    "name": "元素伤害光环",
    "description": "周围友军获得额外火焰, 冰霜, 闪电伤害"
  },
  "monster_aura_essence_daemon_degen": {
    "name": "混沌伤害光环",
    "description": "敌人持续受到混沌伤害"
  },
  "monster_thorns_physical": { "name": "反射", "description": "反射物理伤害" },
  "monster_thorns_elemental": {
    "name": "反射",
    "description": "反射火焰, 冰霜, 闪电伤害"
  },
  "monster_thorns_physical_large": {
    "name": "反射",
    "description": "反射物理伤害"
  },
  "monster_thorns_elemental_large": {
    "name": "反射",
    "description": "反射火焰, 冰霜, 闪电伤害"
  },
  "monster_thorns_bloodline": { "name": "反射", "description": "" },
  "monster_thorns_bloodline_large_model": { "name": "反射", "description": "" },
  "dominated": { "name": "被霸气控制的", "description": "" },
  "dominating_blow_hit_buff": { "name": "被霸气之击击中", "description": "" },
  "immortal_call": { "name": "不朽怒嚎", "description": "你对物理伤害免疫" },
  "vaal_immortal_call": { "name": "瓦尔不朽怒嚎", "description": "你不会死亡" },
  "monty_haul": { "name": "宝藏! ", "description": "掉落测试" },
  "lightning_shield": {
    "name": "暴风之盾",
    "description": "你获得额外的盾牌格挡几率, 成功格挡时重置持续时间. "
  },
  "fire_shield": {
    "name": "熔岩护盾",
    "description": "你获得额外护甲值直到护盾爆炸"
  },
  "flask_utility_critical_strike_chance": {
    "name": "宝钻药剂",
    "description": "你现在比较容易暴击"
  },
  "flask_utility_resist_fire": {
    "name": "红玉药剂",
    "description": "你获得额外火焰抗性和火焰抗性上限"
  },
  "flask_utility_resist_cold": {
    "name": "蓝玉药剂",
    "description": "你获得额外冰霜抗性和冰霜抗性上限"
  },
  "flask_utility_resist_lightning": {
    "name": "黄玉药剂",
    "description": "你获得额外闪电抗性和闪电抗性上限"
  },
  "flask_utility_ironskin": {
    "name": "坚岩药剂",
    "description": "你获得额外的护甲值"
  },
  "flask_utility_sprint": {
    "name": "水银药剂",
    "description": "你获得额外的移动速度"
  },
  "flask_utility_resist_chaos": {
    "name": "紫晶药剂",
    "description": "你获得额外的混沌抗性"
  },
  "flask_utility_phase": {
    "name": "石英药剂",
    "description": "你的移动不会被敌人阻挡, 获得额外几率躲避攻击和法术"
  },
  "flask_utility_evasion": {
    "name": "翠玉药剂",
    "description": "你获得额外的闪避值"
  },
  "flask_utility_stone": {
    "name": "石化药剂",
    "description": "你获得额外的物理伤害减免"
  },
  "flask_utility_aquamarine": {
    "name": "海蓝药剂",
    "description": "你有几率避免受到冰霜伤害"
  },
  "flask_utility_prismatic": {
    "name": "灰岩药剂",
    "description": "你获得额外的元素抗性"
  },
  "flask_utility_smoke": {
    "name": "迷雾药剂",
    "description": "你获得更多的闪避"
  },
  "flask_utility_consecrate": {
    "name": "硫磺药剂",
    "description": "你获得额外的伤害"
  },
  "flask_utility_haste": { "name": "真银药剂", "description": "你获得猛攻" },
  "monster_aura_cannot_die": {
    "name": "不死光环",
    "description": "周围的友军不会死亡"
  },
  "monster_aura_slow": {
    "name": "缓速光环",
    "description": "周围的敌军被缓速"
  },
  "monster_aura_damage_reduction": {
    "name": "减伤光环",
    "description": "周围的友军收到更少伤害"
  },
  "elemental_equilibrium_buff": {
    "name": "元素之相",
    "description": "你正受到元素之相影响. 你的抗性暂时发生了变化. "
  },
  "hidden_monster": { "name": "", "description": "" },
  "block_test": { "name": "格挡测试", "description": "我要挡十个! " },
  "bleeding": {
    "name": "流血",
    "description":
      "你正在流血, 同时受到持续的物理伤害. 移动时将会受到额外的伤害. "
  },
  "bleeding_moving": { "name": "", "description": "" },
  "player_aura_armour": { "name": "坚定光环", "description": "获得额外护甲" },
  "player_aura_evasion": { "name": "优雅光环", "description": "获得额外闪避" },
  "player_aura_resists": {
    "name": "元素净化光环",
    "description": "增加所有元素抗性"
  },
  "player_aura_fire_resist": {
    "name": "火焰净化光环",
    "description": "增加额外火焰抗性"
  },
  "player_aura_cold_resist": {
    "name": "冰霜净化光环",
    "description": "增加额外冰霜抗性"
  },
  "player_aura_lightning_resist": {
    "name": "闪电净化光环",
    "description": "增加额外闪电抗性"
  },
  "player_aura_energy_shield": {
    "name": "纪律光环",
    "description": "增加额外的能量护盾, 增加能量护盾回复率"
  },
  "player_aura_fire_damage": {
    "name": "愤怒光环",
    "description": "增加额外的火焰伤害"
  },
  "player_aura_cold_damage": {
    "name": "憎恨光环",
    "description": "增加等同物理伤害一定数值的额外冰霜伤害"
  },
  "player_aura_lightning_damage": {
    "name": "雷霆光环",
    "description": "增加额外闪电伤害"
  },
  "player_aura_speed": {
    "name": "迅捷光环",
    "description": "增加攻击与施法速度"
  },
  "player_aura_life_regen": {
    "name": "活力光环",
    "description": "增加生命回复"
  },
  "power_shot_hit": {
    "name": "被力量抽取击中",
    "description":
      "如果你在被力量抽取击中的情况下死亡, 你将会产生一个暴击能量球"
  },
  "player_aura_mana_regen": {
    "name": "清晰光环",
    "description": "增加魔力回复"
  },
  "vaal_aura_armour": {
    "name": "瓦尔坚定光环",
    "description": "增加额外护甲和抗性"
  },
  "vaal_aura_life_regen": {
    "name": "瓦尔活力光环",
    "description": "增加生命回复"
  },
  "vaal_aura_no_mana_cost": {
    "name": "瓦尔清晰光环",
    "description": "施放技能不消耗魔力"
  },
  "vaal_aura_dodge": {
    "name": "瓦尔优雅光环",
    "description": "增加额外躲避几率"
  },
  "vaal_aura_energy_shield": {
    "name": "瓦尔纪律光环",
    "description": "增加额外能量护盾, 并且不会因为受到攻击而延迟护盾的回复. "
  },
  "vaal_aura_speed": {
    "name": "瓦尔迅捷光环",
    "description": "额外增加施法, 攻击以及移动速度. "
  },
  "beartrap_debuff": {
    "name": "被陷阱夹住",
    "description": "你被捕熊陷阱夹住了"
  },
  "trap_convert_buff": {
    "name": "变换阵营",
    "description": "你暂时被转换到另一方了"
  },
  "ground_fire_burn": {
    "name": "燃烧地面",
    "description": "你站在燃烧的地面上并持续受到火焰伤害"
  },
  "ground_ice_chill": {
    "name": "冰缓地面",
    "description": "你站在结冰的地面上并将持续被冰缓"
  },
  "ground_tar_slow": {
    "name": "污油地面",
    "description": "你站在布满焦油的地板上且移动速度受到减缓"
  },
  "monster_no_drops_buff": { "name": "", "description": "" },
  "totem_aura_life_regen": {
    "name": "回春图腾光环",
    "description": "增加生命回复"
  },
  "totem_aura_life_mana_regen": {
    "name": "生命与魔力回复图腾光环",
    "description": "增加生命和魔力回复"
  },
  "monster_aura_cold_damage": {
    "name": "冰霜伤害光环",
    "description": "周围友军造成额外冰霜伤害"
  },
  "monster_aura_fire_damage": {
    "name": "火焰伤害光环",
    "description": "周围友军造成额外火焰伤害"
  },
  "monster_aura_lightning_damage": {
    "name": "闪电伤害光环",
    "description": "周围友军造成额外闪电伤害"
  },
  "ambrosia_aura_fire_damage": {
    "name": "火焰伤害光环",
    "description": "周围友军造成额外火焰伤害"
  },
  "amarissa_aura_lightning_damage": {
    "name": "闪电伤害光环",
    "description": "周围友军造成额外闪电伤害"
  },
  "blinded": { "name": "致盲", "description": "你的命中率大幅降低" },
  "monster_aura_always_crit": {
    "name": "必定暴击光环",
    "description": "周围的友军必定暴击"
  },
  "monster_aura_evasion": {
    "name": "闪避光环",
    "description": "周围友军获得额外的闪避"
  },
  "ice_shield": {
    "name": "极地装甲",
    "description": "持续消耗魔力, 但你获得部分的物理及火焰伤害减免. "
  },
  "ice_shield_moving": { "name": "", "description": "" },
  "frozen_damage_increase": {
    "name": "冰冻伤害增加",
    "description": "你将受到更多伤害"
  },
  "red_team": { "name": "红队", "description": "你现在是红队. " },
  "blue_team": { "name": "篮队", "description": "你现在是蓝队. " },
  "minion_red_team": { "name": "红队", "description": "你现在是红队. " },
  "minion_blue_team": { "name": "篮队", "description": "你现在是蓝队. " },
  "trap_red_team": { "name": "红队", "description": "你现在是红队. " },
  "trap_blue_team": { "name": "篮队", "description": "你现在是蓝队. " },
  "cheat_alternate_skill_art": {
    "name": "作弊",
    "description": "你现在使用的是替换的技能模块"
  },
  "lightning_thorns": {
    "name": "闪电护盾",
    "description": "你被击中时将对攻击者射出闪电伤害的投射物。"
  },
  "piety_fire_form": { "name": "", "description": "" },
  "piety_ice_form": { "name": "", "description": "" },
  "piety_transformed_debuff": { "name": "", "description": "" },
  "cheat_blood_override": { "name": "血量金手指", "description": "" },
  "leaving_area_protection": { "name": "", "description": "" },
  "awesomerorybuff": { "name": "", "description": "不死光环" },
  "strdexint": { "name": "", "description": "三相之力" },
  "vinktar_lightning_bond_in_beam": {
    "name": "闪电连接",
    "description": "你正受到闪电连接的闪电伤害"
  },
  "searing_bond_in_beam": {
    "name": "灼热连接",
    "description": "你正受到灼热连接的燃烧伤害"
  },
  "minionstest": { "name": "召唤测试", "description": "测试" },
  "projectiletest": { "name": "投射物测试", "description": "测试" },
  "durationtest": { "name": "持久测试", "description": "测试" },
  "totemtest": { "name": "图腾测试", "description": "测试" },
  "traptest": { "name": "陷阱测试", "description": "测试" },
  "ground_desecration": {
    "name": "腐化地面",
    "description": "你站在腐蚀地面上, 将受到持续的混沌伤害"
  },
  "ground_consecration": { "name": "奉献地面", "description": "获得生命回复" },
  "footstep_cheat": { "name": "脚印", "description": "你正在使用足迹特效" },
  "unique_flask_ghost_reaver": {
    "name": "鬼盗",
    "description": "生命偷取应用于能量护盾"
  },
  "unique_flask_zealots_oath": {
    "name": "狂热者的誓言",
    "description": "生命回复应用于能量护盾"
  },
  "unique_flask_zerphis_last_breath": {
    "name": "泽佛伊的终息",
    "description": "施放技能时, 回复等同魔力消耗一部分的生命"
  },
  "flask_immune_to_damage": { "name": "免疫", "description": "你对伤害免疫" },
  "unique_flask_divination_distillate": {
    "name": "淬炼占卜",
    "description":
      "获得额外物品数量与稀有度增幅, 增加所有元素抗性上限及视野范围. "
  },
  "onslaught": {
    "name": "猛攻",
    "description": "获得额外攻击速度, 施法速度及移动速度. "
  },
  "undying_rage": {
    "name": "不朽狂暴",
    "description": "获得额外物理攻击伤害及移动速度"
  },
  "unique_deaths_oath_aura": {
    "name": "死亡誓约",
    "description": "你将持续受到混沌伤害"
  },
  "unique_deaths_oath_debuff": {
    "name": "死亡誓约",
    "description": "你将持续受到混沌伤害"
  },
  "projectile_homing_test": {
    "name": "投射物返还",
    "description": "你的投射物会返还到自身"
  },
  "birdman_consume_corpse_buff": { "name": "", "description": "" },
  "damage_aura": { "name": "伤害光环", "description": "造成额外伤害" },
  "reave_counter": {
    "name": "超级冲击波",
    "description": "你所使用的冲击波攻击范围更广了"
  },
  "chilling_bond_in_beam": {
    "name": "寒冰射线",
    "description": "你正受到寒冰射线的冰霜伤害及冰缓效果. "
  },
  "additional_totems_test": {
    "name": "额外图腾",
    "description": "你可以召唤额外的图腾"
  },
  "dominus_mark": {
    "name": "神主标记",
    "description": "召唤幻影来阻挠你, 它们会追着你并且进行自爆攻击. "
  },
  "manashield": {
    "name": "魔力护盾",
    "description": "当你受到伤害时, 会优先扣除魔力值而非生命. "
  },
  "proximity_shield_aura": {
    "name": "相位护罩",
    "description": "在力场之外的敌人无法对你造成直接伤害"
  },
  "incinerate_counter": {
    "name": "烧毁",
    "description": "你的烧尽将造成更多伤害并且巨大化"
  },
  "chilled_burn_damage_increase": { "name": "", "description": "" },
  "testnova": { "name": "新星", "description": "" },
  "suppressing_fire": {
    "name": "火力抑制",
    "description": "你的法术和远程攻击受到抑制, 使得射击与施法速度减缓. "
  },
  "ground_lightning_shock": {
    "name": "感电地面",
    "description": "你站在感电地面上, 受到的伤害将会增加. "
  },
  "ground_smoke_blind": {
    "name": "致盲",
    "description": "当你站在烟雾中时命中率将会大幅下降"
  },
  "smoke_mine_movement_speed": {
    "name": "疾跑",
    "description": "你的移动速度增加了"
  },
  "trapdamage": {
    "name": "陷阱、地雷与图腾伤害",
    "description": "陷阱伤害, 地雷伤害, 图腾伤害. "
  },
  "unique_flask_tears_of_the_dybbuk_prince": {
    "name": "戴伯王子之泪",
    "description":
      "对恶魔生物造成额外的伤害, 同时恶魔生物对你造成的伤害将会减少. "
  },
  "movement_speed_buff": {
    "name": "跑的快! ",
    "description": "你的移动速度增加了"
  },
  "proximity_shield_buff": {
    "name": "相位护罩",
    "description": "在力场之外的敌人无法对你造成直接伤害"
  },
  "freeze_mine_cold_resistsance_debuff": {
    "name": "冰冻地雷",
    "description": "你被冰冻地雷冰冻了, 同时将失去冰霜抗性. "
  },
  "corrupted_blood": {
    "name": "腐化之血",
    "description": "你正在流血并受到物理伤害"
  },
  "corrupted_blood_rain": {
    "name": "腐化之血雨",
    "description":
      "你正被血雨攻击而流血并同时受到物理伤害 － 快逃到安全的区域! "
  },
  "shrine_acceleration": {
    "name": "迅速神殿",
    "description": "你动的更快, 且你的投射物速度也获得提升. "
  },
  "shrine_brutal": {
    "name": "狂击神殿",
    "description": "你的攻击造成更多伤害, 会击退敌人且增加敌人被你晕眩的时间. "
  },
  "shrine_thorns": {
    "name": "荆棘神殿",
    "description": "你将反射部分的物理及火焰, 冰霜, 闪电伤害"
  },
  "shrine_regen": {
    "name": "回复神殿",
    "description": "你获得额外的生命及魔力回复"
  },
  "shrine_critical": { "name": "钻石神殿", "description": "你持续造成暴击" },
  "shrine_fire": { "name": "燃烧神殿", "description": "你的周围下起了火雨" },
  "shrine_lightning": {
    "name": "雷霆神殿",
    "description": "你的周围持续的放电"
  },
  "shrine_cold": {
    "name": "霜寒神殿",
    "description": "你的周围将持续散发冰霜新星"
  },
  "shrine_arc": { "name": "静电神殿", "description": "你将会持续散发电弧" },
  "shrine_smoke": { "name": "迷雾神殿", "description": "你的周围环绕着烟雾" },
  "shrine_skeleton": {
    "name": "魔侍神殿",
    "description": "你将被魔侍护卫所围绕"
  },
  "shrine_echoing": {
    "name": "回响神殿",
    "description": "你的技能将会被重复施放"
  },
  "shrine_curses": {
    "name": "邪法神殿",
    "description": "你的打击充满怨念, 会造成随机的诅咒. "
  },
  "shrine_massive": {
    "name": "威猛神殿",
    "description": "你的体型, 生命与范围攻击都获得了强化. "
  },
  "shrine_defence": {
    "name": "坚韧神殿",
    "description": "你获得额外护甲, 闪避值与能量护盾. "
  },
  "shrine_godmode": {
    "name": "圣洁神殿",
    "description": "圣洁之力让你不会受到任何伤害"
  },
  "shrine_resistance": {
    "name": "抗性神殿",
    "description": "你获得额外的元素抗性"
  },
  "farshot": { "name": "远射", "description": "测试" },
  "mine_trap_test": { "name": "地雷陷阱测试", "description": "测试" },
  "animated_armour": { "name": "", "description": "" },
  "tower_demon_explode": { "name": "", "description": "" },
  "unique_flask_blood_of_the_karui": {
    "name": "卡鲁族之血",
    "description":
      "在药剂效果时间内你将无法回复生命, 但效果结束后将会回满生命. "
  },
  "unique_flask_laviangas_cup": {
    "name": "拉维安加的圣杯",
    "description": "在药剂效果时间内你的技能不需消耗魔力"
  },
  "stolen_mods_buff": {
    "name": "猎头者",
    "description": "你获得所击败之稀有怪物的异能"
  },
  "oba_death_buff": {
    "name": "难逃一死",
    "description": "等增益结束后, 我就要回老家结婚了..."
  },
  "ctf_have_red_flag": {
    "name": "红旗背负者",
    "description": "点击右键丢弃. 每一层效果将受到额外 50% 的伤害. "
  },
  "ctf_have_blue_flag": {
    "name": "蓝旗背负者",
    "description": "点击右键丢弃. 每一层效果将受到额外 50% 的伤害. "
  },
  "ctf_have_green_flag": {
    "name": "绿旗背负者",
    "description": "点击右键丢弃. 每一层效果将受到额外 50% 的伤害. "
  },
  "nemesis_transformed": {
    "name": "狂暴之怒",
    "description": "你获得额外攻击, 施法及移动速度, 并且减少受到的伤害. "
  },
  "curse_silence": { "name": "沉默", "description": "你无法施放法术或战吼" },
  "curse_aura_silence": { "name": "沉默", "description": "你无法施放法术" },
  "soul_eater_aura": { "name": "灵魂吞食", "description": "灵魂吞食" },
  "soul_eater": {
    "name": "灵魂吞食",
    "description":
      "你获得额外攻击, 施法速度, 体型获得强化, 并且减少受到的物理, 火焰, 冰霜, 闪电伤害. "
  },
  "frostwall_epk": { "name": "", "description": "" },
  "nemesis_stealth_mode": { "name": "", "description": "" },
  "seawitch_lightning_beam": {
    "name": "闪电连接",
    "description": "你目前正受到闪电连接的闪电伤害"
  },
  "usemax_life_regen": {
    "name": "生命回复",
    "description": "你的生命正在回复"
  },
  "statusailmenttest": { "name": "测试", "description": "测试" },
  "vortex_mine": { "name": "漩涡地雷", "description": "" },
  "charged_blast_counter": {
    "name": "烈焰爆破",
    "description": "你正在使用烈焰爆破"
  },
  "chill_prevention": { "name": "免疫冰缓", "description": "你无法被冰缓" },
  "freeze_prevention": { "name": "免疫冰冻", "description": "你无法被冰冻" },
  "ignite_prevention": { "name": "免疫点燃", "description": "你无法被点燃" },
  "shock_prevention": { "name": "免疫感电", "description": "你无法被感电" },
  "unique_dying_breath_curse_aura": {
    "name": "死亡吐息",
    "description": "你所受到的诅咒效果将会受到强化"
  },
  "unique_dying_breath_damage_aura": {
    "name": "死亡吐息",
    "description": "你会造成额外伤害"
  },
  "int_mission_dying_breath_aura": {
    "name": "不洁伤害",
    "description": "在腐化不死者周围的敌人与友军会造成更多伤害. "
  },
  "sea_witch_screech_debuff": {
    "name": "海妖之嚎",
    "description": "你的移动速度下降了"
  },
  "offering_offensive": {
    "name": "血肉奉献",
    "description": "你的攻击, 施法和移动速度增加. "
  },
  "offering_defensive": {
    "name": "骸骨奉献",
    "description": "你获得格档, 法术格档和格档时回复生命. "
  },
  "unholy_might": {
    "name": "不洁之力",
    "description": "你将造成额外的混沌伤害, 数值依据你的物理伤害而定. "
  },
  "unholy_might_permanent": {
    "name": "不洁之力",
    "description": "你将造成额外的混沌伤害, 数值依据你的物理伤害而定. "
  },
  "unholy_might_from_flask": {
    "name": "不洁之力",
    "description": "你将造成额外的混沌伤害, 数值依据你的物理伤害而定. "
  },
  "daemon_delay": { "name": "", "description": "" },
  "fire_enrage": { "name": "", "description": "" },
  "atziri_fire_charge": { "name": "", "description": "" },
  "atziri_lightning_charge": { "name": "", "description": "" },
  "atziri_physical_charge": { "name": "", "description": "" },
  "vaal_twin_enrage": { "name": "瓦尔之怒", "description": "" },
  "demon_one_enrage": { "name": "", "description": "" },
  "demon_two_enrage": { "name": "", "description": "" },
  "demon_three_enrage": { "name": "", "description": "" },
  "unique_flask_atziris_promise": {
    "name": "女王的允诺",
    "description": "你能从造成的混沌伤害中偷取生命, 并将造成额外的混沌伤害. "
  },
  "kiweth_enrage": { "name": "", "description": "" },
  "pinned": { "name": "被标记", "description": "你已被箭矢锁定" },
  "vaal_cloud_stack": { "name": "", "description": "" },
  "vaal_cloud": { "name": "腐败烟幕", "description": "你将持续受到物理伤害" },
  "cannot_die": { "name": "", "description": "" },
  "atziri_charge_requirement_reduction": { "name": "", "description": "" },
  "atziri_demon_summoning": { "name": "", "description": "" },
  "status_immunity_enrage": { "name": "", "description": "" },
  "summoned_monster_epk_buff": { "name": "", "description": "" },
  "pvp_keep_animated_armour_dead": { "name": "", "description": "" },
  "upheavalbuff": { "name": "动荡", "description": "" },
  "godmode_west": { "name": "强化不朽怒嚎", "description": "" },
  "garena_drops_display_buff": {
    "name": "费尔船长的幸运",
    "description": "费尔船长为您带来幸运! "
  },
  "camoflage": {
    "name": "迷彩",
    "description": "你融入了周围的环境, 获得了额外的躲避以及法术躲避. "
  },
  "unique_flask_forbidden_taste": {
    "name": "禁果",
    "description": "你正持续受到混沌伤害"
  },
  "darkexile_corruption": { "name": "", "description": "" },
  "darkseawitch_corruption": { "name": "", "description": "" },
  "rampage_stack": { "name": "暴走", "description": "@#%*)@#%*@^)" },
  "unique_flask_rumis_concoction": {
    "name": "鲁米的灵药",
    "description": "你获得额外的几率以阻挡攻击和法术"
  },
  "marauder_mission_have_idol": {
    "name": "背负卡鲁之灵",
    "description": "背负卡鲁之灵回到入口"
  },
  "mine_test": {
    "name": "",
    "description": "地雷爆发距离 +%, 地雷持续时间 +%"
  },
  "minion_stat_test": { "name": "", "description": "召唤生物伤害 +%" },
  "cagan_darkness": {
    "name": "黑暗潜伏",
    "description": "能见度, 物品稀有度, 物品数量随着时间递减, 并在击败时增加. "
  },
  "physical_immunity": {
    "name": "物理伤害免疫",
    "description": "你对物理伤害免疫"
  },
  "bleeding_movespeed_penalty": {
    "name": "移动速度减低（流血）",
    "description": "你的移动速度已减低"
  },
  "phasing_buff": {
    "name": "相位转移",
    "description": "你的移动将不再会被敌人所阻碍"
  },
  "mission_relic_grace": { "name": "", "description": "" },
  "mission_duelist_grace": { "name": "", "description": "" },
  "hound_effect_buff": { "name": "", "description": "" },
  "exile_arcane_buff": { "name": "", "description": "" },
  "oba_decapitated": { "name": "", "description": "" },
  "heal": { "name": "", "description": "" },
  "herald_of_ash": {
    "name": "灰烬之捷",
    "description":
      "你造成额外火焰伤害, 并在击败敌人时将溢出的伤害以点燃的方式扩散给附近的敌人"
  },
  "herald_of_ice": {
    "name": "寒冰之捷",
    "description": "你造成额外冰霜伤害, 在粉碎敌人时对附近的敌人造成冰霜伤害"
  },
  "herald_of_thunder": {
    "name": "闪电之捷",
    "description":
      "你造成额外闪电伤害, 并在击败感电状态的敌人时会呼唤一道雷霆降临. "
  },
  "herald_of_thunder_active": { "name": "", "description": "" },
  "cannot_be_damaged": { "name": "伤害免疫", "description": "免疫所有伤害" },
  "spectating_pvp_buff": { "name": "", "description": "" },
  "str_int_mission_mana_regen_relic": { "name": "", "description": "" },
  "display_bodyguard_effect": { "name": "", "description": "" },
  "mission_relic_praying": { "name": "", "description": "" },
  "mission_beast_corrupted": { "name": "", "description": "" },
  "mission_monster_target": { "name": "", "description": "" },
  "dex_mission_enable_pointers": { "name": "", "description": "" },
  "stun_display_buff": { "name": "", "description": "" },
  "visual_display_buff": { "name": "", "description": "" },
  "visual_display_buff_gargoyle": { "name": "", "description": "" },
  "mission_int_buff": { "name": "", "description": "" },
  "fire_damage_and_ignite": {
    "name": "火伤与点燃",
    "description": "火焰伤害与点燃"
  },
  "cold_damage_and_freeze": {
    "name": "冰伤与冰冻",
    "description": "冰霜伤害与冰冻"
  },
  "lightning_damage_and_shock": {
    "name": "电伤与感电",
    "description": "闪电伤害与感电"
  },
  "strdex_mission_fire_damage": {
    "name": "火焰伤害",
    "description": "火焰伤害"
  },
  "strdex_mission_cold_damage": {
    "name": "冰霜伤害",
    "description": "冰霜伤害"
  },
  "strdex_mission_lightning_damage": {
    "name": "闪电伤害",
    "description": "闪电伤害"
  },
  "physical_damage_and_bleed": {
    "name": "物伤与流血",
    "description": "额外伤害与流血"
  },
  "monster_life_flask": { "name": "", "description": "" },
  "spirals": { "name": "测试用", "description": "发射螺旋投射物" },
  "drop_bear_enrage": { "name": "暴怒", "description": "" },
  "sandstorm": { "name": "沙暴", "description": "你正受到持续的物理伤害" },
  "union_of_souls": {
    "name": "聚魂",
    "description": "你从死亡的血族成员中聚集魂魄, 获得力量与体型增大"
  },
  "bloodlines_shrouded": { "name": "", "description": "" },
  "bloodlines_necrovigil": {
    "name": "守护之灵",
    "description": "死亡的血族成员正保护着你"
  },
  "daresso_kneeling": { "name": "", "description": "" },
  "daresso_enrage": { "name": "", "description": "" },
  "bloodlines_damage_charge": { "name": "", "description": "" },
  "bloodlines_speed_charge": { "name": "", "description": "" },
  "cold_thorns": { "name": "寒冰之刺", "description": "被击中时反射冰霜伤害" },
  "monster_aura_burning": {
    "name": "燃烧光环",
    "description": "在光环内持续受到燃烧伤害"
  },
  "monster_aura_chill": {
    "name": "寒冷光环",
    "description": "在光环内所有动作受到缓速"
  },
  "monster_aura_shock": {
    "name": "脆弱光环",
    "description": "在光环内受到额外伤害"
  },
  "static_weapon_buff": {
    "name": "充能打击",
    "description": "充能打击在能量释放时对周围造成范围伤害"
  },
  "hidden_player": { "name": "", "description": "隐蔽" },
  "monster_bloodlines_damage_reduction": { "name": "", "description": "" },
  "bloodlines_invulnerable": { "name": "", "description": "" },
  "bloodlines_vulnerable": { "name": "", "description": "" },
  "torment_touched": { "name": "", "description": "" },
  "torment_possessed": { "name": "", "description": "" },
  "visual_display_buff_not_hidden": { "name": "", "description": "" },
  "torment_cutthroat": {
    "name": "野性残暴",
    "description": "额外物理伤害与攻击速度"
  },
  "unique_flask_taste_of_hate": {
    "name": "酷寒憎恨",
    "description":
      "造成额外冰霜伤害, 同时自身受到依据物理伤害比例的冰霜伤害. 有几率不被冰冻及冰缓"
  },
  "torment_embezzler": {
    "name": "凝滞之息",
    "description": "降低生命, 魔力与能量护盾回复速度"
  },
  "sandstorm_chaos": {
    "name": "混沌沙暴",
    "description": "你持续受到混沌伤害"
  },
  "sandstorm_water": { "name": "漩涡", "description": "你持续受到混沌伤害" },
  "bull_thorns": {
    "name": "狂牛锐角",
    "description": "你被击中时反射物理和火焰, 冰霜, 闪电伤害"
  },
  "damage_aura_skeleton_elite": {
    "name": "伤害光环",
    "description": "你会造成额外伤害"
  },
  "trap_nonplayer_immunity": { "name": "", "description": "" },
  "inspiring_cry": {
    "name": "激励战吼",
    "description": "你造成更多伤害及获得额外魔力回复"
  },
  "kaom_archer_effect": { "name": "", "description": "" },
  "lb_kaom_archer_effect": { "name": "", "description": "" },
  "abyssal_cry": { "name": "深渊战吼", "description": "你的移动速度减慢" },
  "unique_shapers_seed_regeneration": {
    "name": "塑界者之籽",
    "description": "获得生命回复及增加魔力回复"
  },
  "vaal_aura_elemental_damage_healing": {
    "name": "元素之愈",
    "description": "受到火焰, 冰霜, 闪电伤害时将会转化为对你的治疗"
  },
  "kaom_warrior2_effect": { "name": "", "description": "" },
  "kaom_warrior3_effect": { "name": "", "description": "" },
  "fortify": { "name": "护体", "description": "你在被击中时受到的伤害减少" },
  "taunted": { "name": "被嘲讽", "description": "你被嘲讽了! 强制攻击目标!" },
  "blackguardzombie_speedbuff": { "name": "", "description": "" },
  "kaom_fire": { "name": "", "description": "" },
  "taunt_immunity": { "name": "", "description": "" },
  "stacking_ignite": { "name": "点燃", "description": "你身上起火啦! " },
  "stolen_mod_buff": {
    "name": "属性偷窃",
    "description": "击败稀有怪物后随机获得该怪物的一项属性"
  },
  "ice_elemental_buff": {
    "name": "寒冰魔像",
    "description": "在寒冰魔像启动时增加命中和暴击率"
  },
  "fire_elemental_buff": {
    "name": "烈焰魔像",
    "description": "在烈焰魔像启动时增加伤害"
  },
  "chaos_elemental_buff": {
    "name": "混沌魔像",
    "description": "在混沌魔像启动时获得额外物理伤害减伤"
  },
  "lightning_elemental_buff": {
    "name": "雷电魔像",
    "description": "在雷电魔像启动时获得额外攻击速度和施法速度"
  },
  "culling_strike_aura": {
    "name": "存在王者之刃",
    "description": "附近有友军使用王者之刃时, 你的法术获得终结效果. "
  },
  "increased_item_rarity_aura": {
    "name": "存在王者之刃",
    "description":
      "附近有友军使用王者之刃时, 你的法术获得终结效果和增加物品稀有度. "
  },
  "piety_fire_form_stacking_damage_taken": {
    "name": "派蒂之怒",
    "description": "每迭加一层派蒂之怒将会受到更多伤害"
  },
  "enduring_cry_life_regeneration": {
    "name": "坚决战吼",
    "description": "获得生命回复"
  },
  "flame_golem_effects": { "name": "", "description": "" },
  "flame_golem_summoned_effects": { "name": "", "description": "" },
  "flame_golem_runic_effects": { "name": "", "description": "" },
  "new_punishment_buff": {
    "name": "惩戒者",
    "description": "你造成更多近战伤害并获得额外攻击速度"
  },
  "totem_placement_buff": { "name": "", "description": "" },
  "new_arctic_armour": {
    "name": "极地装甲",
    "description":
      "击中敌人时造成冰缓. 移动时造成冰结地面. 当静止不动时减少受到的物理及火焰伤害. "
  },
  "new_arctic_armour_stationary": { "name": "", "description": "" },
  "unique_flask_lions_roar": {
    "name": "狮吼",
    "description": "造成更多近战物理伤害并击退敌人"
  },
  "revenant_revive_possessed": { "name": "", "description": "" },
  "revenant_revive_explode": { "name": "", "description": "" },
  "unique_flask_chaos_damage_damages_es": {
    "name": "闪耀精华",
    "description": "混沌伤害无法穿透能量护盾"
  },
  "unique_flask_es_regen": { "name": "闪耀精华", "description": "" },
  "blood_rage_xandro": {
    "name": "鲜血狂怒",
    "description":
      "持续消耗生命, 生命偷取, 增加攻击速度. 每击败一个敌人获得一个狂怒能量球. "
  },
  "malachai_invulnerable": { "name": "伤害免疫", "description": "" },
  "piety_ally_beam": {
    "name": "派蒂光束",
    "description": "你目前正受到闪电连接的闪电伤害. "
  },
  "exploding_storm_buff": { "name": "", "description": "" },
  "diamond_storm": { "name": "刺针风暴", "description": "你总是造成暴击. " },
  "uber_diamond_storm": {
    "name": "苛责风暴",
    "description": "你总是造成暴击. "
  },
  "replenishing_storm": {
    "name": "回复风暴",
    "description": "你获得额外的生命及魔力回复. "
  },
  "echoing_storm": {
    "name": "回声风暴",
    "description": "你的技能将会被重复施放. "
  },
  "divine_storm": { "name": "神圣风暴", "description": "你不会受到任何伤害. " },
  "rarity_storm": {
    "name": "闪光风暴",
    "description": "物品稀有度及数量提升. "
  },
  "uber_rarity_storm": {
    "name": "辐射风暴",
    "description": "物品稀有度及数量提升. "
  },
  "massive_storm": {
    "name": "巨化风暴",
    "description": "你的体型, 生命与伤害都获得了强化. "
  },
  "tiny_storm": {
    "name": "缩小风暴",
    "description": "你的体型, 生命与伤害都已降低. "
  },
  "fire_damage_storm": {
    "name": "滚溢风暴",
    "description":
      "你的部分物理伤害转换为火焰伤害, 你的攻击必定点燃敌人, 并使你的火焰伤害增加. "
  },
  "cold_damage_storm": {
    "name": "颤抖风暴",
    "description":
      "你的部分物理伤害转换为冰霜伤害, 你的攻击必定冰冻敌人, 并使你的冰霜伤害增加. "
  },
  "lightning_damage_storm": {
    "name": "激昂风暴",
    "description":
      "你的部分物理伤害转换为闪电伤害, 你的攻击必定感电敌人, 并使你的闪电伤害增加. "
  },
  "smoke_trail_storm": {
    "name": "环绕风暴",
    "description": "你的周围环绕着烟雾. "
  },
  "corpse_devour_storm": {
    "name": "蚕食风暴",
    "description": "消耗附近的灵柩回复你的生命值. "
  },
  "projectile_nova_storm": {
    "name": "裂片风暴",
    "description": "以新星状投射攻击. 你会额外投射 4 发投射物. 增加范围效果. "
  },
  "veil_storm": {
    "name": "幕蔽风暴",
    "description": "元素抗性归零, 能见度降低. "
  },
  "voltaxic_storm": {
    "name": "深渊风暴",
    "description": "你造成的伤害一部分转换为混沌伤害. "
  },
  "phasing_storm": {
    "name": "虚无风暴",
    "description": "你的移动将不再会被敌人所阻碍. 你有几率躲避攻击和法术. "
  },
  "corrupted_drops_storm": {
    "name": "腐化风暴",
    "description":
      "你找到的物品皆已腐化. 身上有此增益效果的敌人掉落已腐化物品. "
  },
  "drop_as_sell_price_storm": {
    "name": "转化风暴",
    "description": "除通货, 宝石, 地图以外, 你发现的非传奇物品以售价掉落. "
  },
  "quality_drops_storm": {
    "name": "精炼风暴",
    "description": "你发现的物品品质优良. 此增益效果怪物会掉落品质优良物品. "
  },
  "identify_items_storm": {
    "name": "鉴识风暴",
    "description": "你发现的物品将会被鉴定. "
  },
  "arcane_storm": {
    "name": "秘能风暴",
    "description":
      "你获得额外的火焰, 冰霜, 闪电伤害和施法速度. 每次施法将在 1 秒内回复 10 生命值. "
  },
  "status_immunity_storm": {
    "name": "抗性风暴",
    "description":
      "你无法被冰缓, 冰冻, 点燃, 或感电. 你获得额外的元素抗性以及元素抗性上限. "
  },
  "ground_spore_damage": { "name": "玛拉凯孢子", "description": "" },
  "flask_bonus_item_rarity": { "name": "增加物品稀有度", "description": "" },
  "map_boss_duet_enrage": { "name": "", "description": "" },
  "ground_spores": {
    "name": "地面凯孢子",
    "description": "你站在地面凯孢子上, 正在受到物理伤害. "
  },
  "new_phase_run": {
    "name": "暗影迷踪",
    "description":
      "你正在相位转移, 你能穿过敌人, 增加移动速度, 较不容易被怪物看见, 并且造成更多近战伤害. "
  },
  "new_phase_run_damage": {
    "name": "暗影迷踪伤害",
    "description": "你造成更多近战伤害. "
  },
  "tempest_soul_eater": { "name": "消耗风暴", "description": "你有噬魂者. " },
  "static_tether": { "name": "静电锁链", "description": "" },
  "flask_bonus_mana_regeneration_rate": { "name": "", "description": "" },
  "flask_bonus_flask_charge_recovery": { "name": "", "description": "" },
  "frost_bomb": {
    "name": "霜害",
    "description": "你的冰霜抗性和生命回复速度降低了. "
  },
  "lightning_bomb": {
    "name": "雷祸",
    "description": "你的闪电抗性和生命回复速度降低了. "
  },
  "borrowed_power_lightning_aura": { "name": "力量借贷", "description": "" },
  "disable_weapons_buff": {
    "name": "武器失效",
    "description": "你获得猛攻, 并且你的武器处于失效状态. "
  },
  "sawblade_damage": { "name": "死亡伦巴", "description": "" },
  "usemax_mana_regen": {
    "name": "魔力回复",
    "description": "你的魔力正在回复"
  },
  "righteous_lightning": {
    "name": "正义怒雷",
    "description": "对周围敌人造成闪电伤害, 持续扣除魔力"
  },
  "righteous_lightning_aura": {
    "name": "正义怒雷",
    "description": "你在敌人的正义怒雷中持续受到伤害"
  },
  "life_leech_damage": {
    "name": "生命偷取伤害",
    "description": "你正在受到敌人生命偷取造成的混沌伤害"
  },
  "enchantment_added_fire_damage": { "name": "", "description": "" },
  "enchantment_dodge_chance": { "name": "", "description": "" },
  "talisman_monster": { "name": "魔符", "description": "" },
  "caustic_cloud": {
    "name": "腐蚀毒云",
    "description": "你正受到腐蚀毒云的混沌伤害. "
  },
  "enchantment_reduced_mana_cost": { "name": "", "description": "" },
  "enchantment_stun_avoid": { "name": "", "description": "" },
  "enchantment_spell_dodge": { "name": "", "description": "" },
  "enchantment_attack_and_cast_speed": { "name": "", "description": "" },
  "enchantment_added_cold_damage": { "name": "", "description": "" },
  "enchantment_life_and_mana_leech": { "name": "", "description": "" },
  "enchantment_life_mana_regen": { "name": "", "description": "" },
  "attack_speed_when_hit": { "name": "", "description": "" },
  "negate_move_speed_increase": { "name": "", "description": "" },
  "berserker_life_and_mana_leech": { "name": "", "description": "" },
  "added_fire_damage": {
    "name": "火焰伤害",
    "description": "你造成额外物理伤害比例的火焰伤害"
  },
  "attack_and_cast_speed": {
    "name": "攻击和施法速度",
    "description": "你的攻击和施法速度增加"
  },
  "physical_damage_stacking": {
    "name": "狂暴催化",
    "description": "你的物理伤害和移动速度增加"
  },
  "block_chance": { "name": "", "description": "你的格档几率增加" },
  "damage": { "name": "", "description": "你的物理伤害增加" },
  "taunted_special": {
    "name": "",
    "description": "增加你被晕眩的几率和增加受到的伤害"
  },
  "damage_and_movement_speed": {
    "name": "启发",
    "description": "增加伤害和移动速度"
  },
  "siphon_damage": { "name": "灵魂吸取", "description": "你受到持续混沌伤害" },
  "contagion": { "name": "瘟疫", "description": "你受到持续混沌伤害" },
  "hinder": { "name": "缓速", "description": "你的移动速度降低" },
  "wither_resistance": {
    "name": "死亡凋零",
    "description": "你受到的混沌伤害增加"
  },
  "siphon_leech": {
    "name": "灵魂吸取回复",
    "description": "你正在从灵魂吸取回复生命"
  },
  "rallying_cry_damage_added_as_mana": {
    "name": "激励战吼伤害回魔力",
    "description": "你受到的部分伤害回复魔力"
  },
  "offering_of_judgement_fire": {
    "name": "审判奉献",
    "description": "你受到火焰伤害"
  },
  "offering_of_judgement_chaos": {
    "name": "审判奉献",
    "description": "你受到混沌伤害"
  },
  "offering_of_judgement_counter": { "name": "", "description": "" },
  "her_blessing": {
    "name": "女神的祝福",
    "description":
      "你得到女神的祝福, 每秒钟受到等同你 33% 最大生命以及最大能量护盾的火焰伤害. "
  },
  "maim": { "name": "瘫痪", "description": "你被瘫痪而移动速度降低. " },
  "lightning_flask": {
    "name": "维克塔血器",
    "description": "你与周围的敌人受到感电, 你的闪电伤害会偷取生命及魔力. "
  },
  "lightning_flask_attack_damage": {
    "name": "维克塔血器",
    "description": "你的攻击造成额外闪电伤害. "
  },
  "lightning_flask_spell_damage": {
    "name": "维克塔血器",
    "description": "你的法术造成额外闪电伤害. "
  },
  "lightning_flask_physical_to_lightning": {
    "name": "维克塔血器",
    "description": "你一部分的物里伤害转换为闪电伤害. "
  },
  "lightning_flask_lightning_penetration": {
    "name": "维克塔血器",
    "description": "你造成的伤害可穿透敌人的闪电抗性. "
  },
  "shock_aura": {
    "name": "感电光环",
    "description": "你在感电光环中将受到额外的伤害. "
  },
  "trap_pinned": { "name": "刺穿", "description": "" },
  "enchantment_physical_to_fire": { "name": "", "description": "" },
  "enchantment_physical_to_cold": { "name": "", "description": "" },
  "enchantment_physical_to_lightning": { "name": "", "description": "" },
  "enchantment_added_chaos_damage": { "name": "", "description": "" },
  "stacking_increased_spell_damage": { "name": "", "description": "" },
  "templar_ascendency_movement_speed": {
    "name": "升华效果 (隐形)",
    "description": ""
  },
  "guardian_warcry": { "name": "升华效果 (隐形)", "description": "" },
  "avoid_stun_staff_aura": {
    "name": "长杖精通",
    "description": "你获得了来自守护者的晕眩免疫"
  },
  "labyrinth_lava_aura": {
    "name": "熔岩",
    "description": "能量护盾 普通/残酷/无情, 生命 普通/残酷/无情"
  },
  "roomba_damage": { "name": "死亡伦巴", "description": "" },
  "flying_roomba_damage": { "name": "飞舞死亡伦巴", "description": "" },
  "offering_of_judgement_ground": { "name": "", "description": "" },
  "curse_damage_taken": { "name": "", "description": "" },
  "increased_crit_chance": { "name": "", "description": "" },
  "increased_minion_damage": { "name": "", "description": "" },
  "increased_damage": { "name": "", "description": "" },
  "damage_taken": { "name": "", "description": "" },
  "avoid_stun": { "name": "升华", "description": "" },
  "spinning_blade_damage": { "name": "回旋之刃", "description": "" },
  "stacking_movement_speed_buff": {
    "name": "增加移动速度",
    "description": "你的移动速度增加了"
  },
  "nightwane_effects": { "name": "", "description": "" },
  "increased_elemental_damage_taken": {
    "name": "元素伤害减免",
    "description": ""
  },
  "mana_and_es_regeneration": { "name": "", "description": "" },
  "vinktar_boss_buff": { "name": "", "description": "" },
  "grant_es_to_nearby_allies": {
    "name": "信念之环",
    "description": "你获得了来自守护者的能量护盾"
  },
  "grant_armour_to_nearby_allies": {
    "name": "信念之环",
    "description": "你获得了来自守护者的护甲"
  },
  "singularity_aura": { "name": "奇异", "description": "你陷入了奇异的领域中" },
  "power_symbol_aura": { "name": "", "description": "" },
  "gargoyle_statue_buff": { "name": "", "description": "" },
  "izaro_fire_buff_phase1": { "name": "", "description": "额外火焰伤害" },
  "izaro_fire_buff": { "name": "", "description": "额外火焰伤害" },
  "izaro_cold_buff_phase1": { "name": "", "description": "额外冰霜伤害" },
  "izaro_cold_buff": { "name": "", "description": "额外冰霜伤害" },
  "izaro_lightning_buff_phase1": { "name": "", "description": "额外闪电伤害" },
  "izaro_lightning_buff": { "name": "", "description": "额外闪电伤害" },
  "izaro_physical_buff_phase1": { "name": "", "description": "增加物理伤害" },
  "izaro_physical_buff": { "name": "", "description": "增加物理伤害" },
  "izaro_ignite_buff_phase1": {
    "name": "",
    "description": "额外火焰伤害和点燃几率"
  },
  "izaro_ignite_buff": { "name": "", "description": "额外火焰伤害和点燃几率" },
  "izaro_freeze_buff_phase1": {
    "name": "",
    "description": "额外冰霜伤害和冰冻几率"
  },
  "izaro_freeze_buff": { "name": "", "description": "额外冰霜伤害和冰冻几率" },
  "izaro_shock_buff_phase1": {
    "name": "",
    "description": "额外闪电伤害和感电几率"
  },
  "izaro_shock_buff": { "name": "", "description": "额外闪电伤害和感电几率" },
  "izaro_bleed_buff_phase1": { "name": "", "description": "额外伤害和流血" },
  "izaro_bleed_buff": { "name": "", "description": "额外伤害和流血" },
  "vinktar_lightning_bond": {
    "name": "维克塔闪电连接",
    "description": "你正受到连接"
  },
  "killed_rare_monsters_drop_uniques": { "name": "", "description": "" },
  "savage_hit_life_leech": {
    "name": "愤怒之拥",
    "description": "获得额外生命偷取, 伤害和攻击速度"
  },
  "savage_hit_damage": { "name": "升华效果 (隐形)", "description": "" },
  "savage_hit_attack_cast_speed": {
    "name": "升华效果 (隐形)",
    "description": ""
  },
  "savage_hit_attack_speed": { "name": "升华效果 (隐形)", "description": "" },
  "melee_physical_damage": {
    "name": "坚韧活力",
    "description": "你获得了来自守护者力量的额外进战物理伤害"
  },
  "grasping_ornaments_slow_aura": {
    "name": "迟缓束缚",
    "description":
      "你处于迟缓束缚的范围内, 你的攻击速度, 移动速度和施法速度都降低了"
  },
  "grasping_tentacles_slow_aura": {
    "name": "迟缓之触",
    "description":
      "你处于迟缓之触的范围内, 你的攻击速度, 移动速度和施法速度都降低了"
  },
  "labyrinth_boss_grace": { "name": "", "description": "" },
  "izaro_summon_lieutenant_delay": { "name": "", "description": "" },
  "shield_defence_aura": {
    "name": "盾牌精通",
    "description": "你获得了来自守护者之盾的额外防御"
  },
  "labyrinth_trap_bleed": { "name": "迷宫陷阱效果", "description": "" },
  "mine_detonation": { "name": "升华效果 (隐形)", "description": "" },
  "augry_of_penitence": {
    "name": "忏悔之兆",
    "description":
      "你所造成的火焰, 冰霜, 闪电伤害降低了, 且受到的火焰, 冰霜, 闪电伤害增加了. "
  },
  "labyrinth_power_symbol_shield": { "name": "WIP", "description": "" },
  "awaken_gargoyle": { "name": "WIP", "description": "" },
  "spell_damage_increase": { "name": "升华效果 (隐形)", "description": "" },
  "attack_damage_increase": { "name": "升华效果 (隐形)", "description": "" },
  "attack_speed_increase": { "name": "升华效果 (隐形)", "description": "" },
  "cast_speed_increase": { "name": "升华效果 (隐形)", "description": "" },
  "life_es_and_mana_recovery": { "name": "升华效果 (隐形)", "description": "" },
  "rock_golem_buff": {
    "name": "巨石魔像",
    "description": "在巨石魔像启动时获得额外生命回复"
  },
  "talisman_totem_effects": { "name": "", "description": "" },
  "spike_trap_immunity": { "name": "", "description": "" },
  "labyrinth_arrow_slow": { "name": "", "description": "" },
  "shrink": {
    "name": "缩小",
    "description": "你被缩小了. 将受到更多的伤害, 并造成更少的伤害."
  },
  "lightning_eye_effects": { "name": "", "description": "" },
  "talisman_degen": {
    "name": "骨骼震荡",
    "description": "你正从骨骼震荡受到持续的物理伤害. "
  },
  "blade_vortex_counter": {
    "name": "飞刃风暴",
    "description": "你周围的飞刃风暴对于范围内的敌人造成伤害"
  },
  "soul_eater_from_stat_parent": {
    "name": "",
    "description": "当使用药剂对付噬魂者时获得增益"
  },
  "LocustSwarmStackingDegenAuraFire": {
    "name": "火焰飞虫",
    "description": "你正受到火焰飞虫的火焰伤害"
  },
  "LocustSwarmStackingDegenAuraCold": {
    "name": "寒冰飞虫",
    "description": "你正受到寒冰飞虫的冰霜伤害"
  },
  "LocustSwarmStackingDegenAuraLightning": {
    "name": "闪电飞虫",
    "description": "你正受到闪电飞虫的闪电伤害"
  },
  "rigwald_channeling": { "name": "瑞佛狼王弹幕", "description": "" },
  "blade_vortex": { "name": "", "description": "" },
  "elemental_overload": {
    "name": "元素超载",
    "description": "你获得了更多火焰, 冰霜, 闪电伤害"
  },
  "frost_nova_counter": {
    "name": "极霜新星",
    "description": "你的冰霜伤害增加了"
  },
  "izaro_pylon_temporal_chains_on_hit": {
    "name": "",
    "description": "击中时附加时空锁炼"
  },
  "izaro_pylon_elemental_weakness_on_hit": {
    "name": "",
    "description": "击中时附加元素要害"
  },
  "izaro_pylon_vulnerability_on_hit": {
    "name": "",
    "description": "击中时附加脆弱"
  },
  "heirophant_attack_and_spell_damage": {
    "name": "攻击和法术伤害",
    "description": "你的伤害增加了"
  },
  "heirophant_additional_totems": { "name": "更多图腾", "description": "" },
  "petrified": { "name": "石化", "description": "你被石化了。" },
  "flask_petrification": {
    "name": "NAME OF FLASK GOES HERE",
    "description": "你被石化了并受到较少的物理伤害"
  },
  "blight": { "name": "枯萎", "description": "你正在受到持续的混沌伤害" },
  "flask_bonus_poison_immunity": {
    "name": "免疫中毒",
    "description": "药剂作用期间免疫中毒"
  },
  "flask_bonus_physical_damage_reduction_percent": {
    "name": "WIP",
    "description": ""
  },
  "life_regen_from_spread_poison": { "name": "生命回复", "description": "" },
  "elementalist_increased_fire_damage": {
    "name": "升华效果 (隐形)",
    "description": ""
  },
  "elementalist_increased_lightning_damage": {
    "name": "升华效果 (隐形)",
    "description": ""
  },
  "elementalist_increased_cold_damage": {
    "name": "升华效果 (隐形)",
    "description": ""
  },
  "elementalist_increased_elemental_damage": {
    "name": "升华效果 (隐形)",
    "description": ""
  },
  "elementalist_cold_penetration": {
    "name": "升华效果 (隐形)",
    "description": ""
  },
  "elementalist_fire_penetration": {
    "name": "升华效果 (隐形)",
    "description": ""
  },
  "elementalist_lightning_penetration": {
    "name": "升华效果 (隐形)",
    "description": ""
  },
  "elemental_conflux": {
    "name": "元素汇流",
    "description": "你的所有伤害都能冰冻, 感电, 和点燃"
  },
  "elementalist_increased_fire_damage_taken": {
    "name": "升华效果 (隐形)",
    "description": ""
  },
  "elementalist_increased_lightning_damage_taken": {
    "name": "升华效果 (隐形)",
    "description": ""
  },
  "elementalist_increased_cold_damage_taken": {
    "name": "升华效果 (隐形)",
    "description": ""
  },
  "elementalist_increased_elemental_damage_cooldown": {
    "name": "升华效果 (隐形)",
    "description": ""
  },
  "occultist_non_chaos_to_chaos_damage": {
    "name": "升华效果 (隐形)",
    "description": ""
  },
  "occultist_nearby_enemies_chaos_resist_life_regen": {
    "name": "虚无之塔",
    "description": "你因为在秘术家的周围降低了生命回复和混沌抗性"
  },
  "occultist_no_energy_shield_recharge_delay": {
    "name": "升华效果 (隐形)",
    "description": ""
  },
  "izaro_elemental_fire_buff_phase1": {
    "name": "",
    "description": "友军造成额外火焰伤害"
  },
  "izaro_elemental_fire_buff": {
    "name": "火焰伤害光环",
    "description": "友军造成额外火焰伤害"
  },
  "izaro_elemental_cold_buff_phase1": {
    "name": "",
    "description": "友军造成额外冰霜伤害"
  },
  "izaro_elemental_cold_buff": {
    "name": "冰霜伤害光环",
    "description": "友军造成额外冰霜伤害"
  },
  "izaro_elemental_lightning_buff_phase1": {
    "name": "",
    "description": "友军造成额外闪电伤害"
  },
  "izaro_elemental_lightning_buff": {
    "name": "闪电伤害光环",
    "description": "友军造成额外闪电伤害"
  },
  "charged_attack": {
    "name": "刀刃乱舞",
    "description": "增加刀刃乱舞的额外总伤害"
  },
  "petrify_enrage": { "name": "WIP", "description": "" },
  "occultist_stacking_es_recovery_per_minute_percent": {
    "name": "升华效果 (隐形)",
    "description": "你正在回复能量护盾"
  },
  "izaro_chronos_statue_damage_phase1": {
    "name": "",
    "description": "额外格挡几率"
  },
  "izaro_chronos_statue_damage": { "name": "", "description": "额外格挡几率" },
  "izaro_chronos_statue_speed_phase1": {
    "name": "",
    "description": "额外法术格挡几率"
  },
  "izaro_chronos_statue_speed": {
    "name": "",
    "description": "额外法术格挡几率"
  },
  "izaro_chronos_statue_damage_taken_phase1": {
    "name": "",
    "description": "额外躲避法术几率和躲避攻击几率"
  },
  "izaro_chronos_statue_damage_taken": {
    "name": "",
    "description": "额外躲避法术几率和躲避攻击几率"
  },
  "izaro_gargoyles_damage_buff_phase1": {
    "name": "伊泽洛伤害",
    "description": "伊泽洛的伤害增加了"
  },
  "izaro_gargoyles_damage_buff": {
    "name": "伊泽洛伤害",
    "description": "伊泽洛的伤害增加了"
  },
  "izaro_gargoyles_speed_buff_phase1": {
    "name": "伊泽洛速度",
    "description": "伊泽洛的攻击, 施法, 和移动速度都增加了"
  },
  "izaro_gargoyles_speed_buff": {
    "name": "伊泽洛速度",
    "description": "伊泽洛的攻击, 施法, 和移动速度都增加了"
  },
  "izaro_gargoyles_damage_taken_buff_phase1": {
    "name": "伊泽洛受到伤害",
    "description": "伊泽洛受到的伤害减少了"
  },
  "izaro_gargoyles_damage_taken_buff": {
    "name": "伊泽洛受到伤害",
    "description": "伊泽洛受到的伤害减少了"
  },
  "izaro_pedestals_physical_damage_reduction_buff_phase 1": {
    "name": "",
    "description": "增加物理伤害减免"
  },
  "izaro_pedestals_physical_damage_reduction_buff": {
    "name": "",
    "description": "增加物理伤害减免"
  },
  "izaro_pedestals_physical_damage_buff_phase 1": {
    "name": "",
    "description": "增加物理伤害"
  },
  "izaro_pedestals_physical_damage_buff": {
    "name": "",
    "description": "增加物理伤害"
  },
  "izaro_pedestals_additional_energy_shield_phase 1": {
    "name": "",
    "description": "额外能量护盾"
  },
  "izaro_pedestals_additional_energy_shield": {
    "name": "",
    "description": "额外能量护盾"
  },
  "izaro_charge": {
    "name": "狂怒球",
    "description": "每个狂怒球赋予更多伤害和增加攻击与施法速度"
  },
  "izaro_super_charge": { "name": "超级狂怒球", "description": "" },
  "offering_spirit": {
    "name": "灵魂奉献",
    "description": "你拥有额外能量护盾, 元素抗性, 并造成额外物理伤害的混沌伤害"
  },
  "totem_aura_chieftain": {
    "name": "酋长图腾光环",
    "description":
      "你在酋长的图腾周围被降低了伤害, 并且增加受到的物理和火焰伤害. "
  },
  "guardian_share_charges_with_party_members_in_aura": {
    "name": "升华效果 (隐形)",
    "description": "在该光环内你会和队员共享能量球"
  },
  "guardian_conduit_aura_enemies": {
    "name": "升华效果 (隐形)",
    "description": "你无法获得能量球. "
  },
  "guardian_dispel_cooldown": { "name": "升华效果 (隐形)", "description": "" },
  "guardian_life_regen": { "name": "升华效果 (隐形)", "description": "" },
  "izaro_disrupter_inactive": { "name": "", "description": "" },
  "izaro_buff_loot_bonus": { "name": "", "description": "" },
  "melee_ancestor_totem_attack_speed": { "name": "", "description": "" },
  "slash_ancestor_totem_phys_added_as_fire": { "name": "", "description": "" },
  "slam_ancestor_totem_melee_damage": { "name": "", "description": "" },
  "guardian_cannot_be_stunned_aura": {
    "name": "升华效果 (隐形)",
    "description": ""
  },
  "izaro_pedestal_timer_buff": { "name": "", "description": "" },
  "lightning_golem_wrath": {
    "name": "闪电魔像愤怒",
    "description": "赋予额外闪电伤害"
  },
  "chronos_statues_buff": { "name": "", "description": "" },
  "damage_increase_when_killed_bleeding_enemy": {
    "name": "",
    "description": ""
  },
  "damage_increase_when_killed_cursed_enemy": { "name": "", "description": "" },
  "increased_minion_attack_and_cast_speed": { "name": "", "description": "" },
  "increased_attack_and_cast_speed": { "name": "", "description": "" },
  "curse_enemy_chaos_resistance": { "name": "", "description": "" },
  "guardian_increased_attack_and_cast_speed": { "name": "", "description": "" },
  "guardian_increased_damage": { "name": "", "description": "" },
  "champion_aura_increased_damage_under_fortify": {
    "name": "启发",
    "description": "一名有护体的升华使徒增加了你的伤害. "
  },
  "enrage_buff": { "name": "", "description": "" },
  "elemental_penetration_from_mine_detonation": {
    "name": "",
    "description": ""
  },
  "have_killed_recently": { "name": "", "description": "" },
  "number_of_times_have_been_hit_recently": { "name": "", "description": "" },
  "have_been_crit_recently": { "name": "", "description": "" },
  "have_crit_recently": { "name": "", "description": "" },
  "have_taken_attack_damage_recently": { "name": "", "description": "" },
  "have_taken_spell_damage_recently": { "name": "", "description": "" },
  "have_used_a_warcry_recently": { "name": "", "description": "" },
  "have_been_savage_hit_recently": { "name": "", "description": "" },
  "have_hit_an_enemy_recently": { "name": "", "description": "" },
  "chronos_statue_life_regen": { "name": "雕像生命回复", "description": "" },
  "perandus_gold_spectre_buff": { "name": "", "description": "" },
  "perandus_chest_protection": { "name": "守护", "description": "" },
  "perandus_chest_fire_empowered": { "name": "火焰强化", "description": "" },
  "perandus_chest_cold_empowered": { "name": "冰霜强化", "description": "" },
  "perandus_chest_lightning_empowered": {
    "name": "闪电强化",
    "description": ""
  },
  "perandus_chest_physical_empowered": {
    "name": "物理强化",
    "description": ""
  },
  "bane_of_the_loyal": {
    "name": "忠臣之灾",
    "description": "你下次攻击的将军将立即死亡. "
  },
  "heart_of_the_gargoyle": {
    "name": "石像之心",
    "description": "你下次攻击的石像将立即死亡. "
  },
  "cube_of_absorption": {
    "name": "融合方晶",
    "description": "你下次处碰的通道将会被永久封闭. "
  },
  "orb_of_elemental_essence": {
    "name": "元素核心之球",
    "description": "你下次攻击的元素核心将立即死亡. "
  },
  "rod_of_detonation": {
    "name": "爆裂之杖",
    "description": "你下次攻击的水晶塔将立即被摧毁. "
  },
  "sand_of_eternity": {
    "name": "永恒之沙",
    "description": "你下次攻击的魔偶将不会再回复生命. "
  },
  "cogs_of_disruption": {
    "name": "瓦解之轮",
    "description": "你下一次使用的电极阻断器在短暂的持续时间后会重新启动. "
  },
  "portal_shredder": {
    "name": "传送门破坏者",
    "description": "你下次所点击的传送门将立即被摧毁. "
  },
  "perandus_chest_revive_marker": { "name": "", "description": "" },
  "active_offering": {
    "name": "待处理请求",
    "description": "你有一个待处理的请求"
  },
  "ground_maelstrom_chill": {
    "name": "漩涡地面",
    "description": "你正受到漩涡的伤害. "
  },
  "aura_increased_damage_taken": {
    "name": "无尽之伤",
    "description": "你受到的所有伤害增加"
  },
  "aura_damage_on_movement_skill_use": {
    "name": "无尽之危",
    "description": "使用移动技能时会受到伤害"
  },
  "savage_hit_life_regen": {
    "name": "奋勇进军生命回复",
    "description": "获得生命回复"
  },
  "overflowing_chalice": {
    "name": "满溢圣杯",
    "description": "此药剂效果作用时增加你获得的药剂充能. "
  },
  "have_killed_a_taunted_enemy_recently": { "name": "", "description": "" },
  "shavronne_torment_aura": {
    "name": "黑影薛朗之光环",
    "description": "友方获得无法被混沌伤害穿透的能量护盾"
  },
  "flask_bonus_flask_charges_gained": {
    "name": "",
    "description": "在药剂作用期间, 该药剂获得额外充能速度"
  },
  "goddess_slow": { "name": "缓慢", "description": "你的移动速度降低了" },
  "have_pierced_recently": { "name": "", "description": "" },
  "goddess_beam": { "name": "上帝之光", "description": "你正在受到燃烧伤害" },
  "have_killed_a_maimed_enemy_recently": { "name": "", "description": "" },
  "have_taunted_an_enemy_recently": { "name": "", "description": "" },
  "guardian_additional_block_chance": {
    "name": "生化效果(不可见)",
    "description": ""
  },
  "guardian_block_cooldown": { "name": "生化效果(不可见)", "description": "" },
  "blocked_unique_enemy_hit_recently": {
    "name": "生化效果(不可见)",
    "description": ""
  },
  "elementalist_increased_area_of_effect": {
    "name": "生化效果(不可见)",
    "description": ""
  },
  "guardian_increased_elemental_resist": {
    "name": "生化效果(不可见)",
    "description": ""
  },
  "pale_court_invulnerability": { "name": "", "description": "" },
  "pale_court_ghost_invulnerability": { "name": "", "description": "" },
  "intimidated": { "name": "被恐吓", "description": "你受到了威吓" },
  "number_of_corpses_consumed_recently": { "name": "", "description": "" },
  "flask_cannot_be_stunned": { "name": "", "description": "" },
  "ascendancy_life_leech": { "name": "", "description": "" },
  "kiaras_determination": {
    "name": "奇亚拉的决心",
    "description": "药剂作用期间, 你免疫冰冻, 冰缓, 诅咒以及晕眩. "
  },
  "prophecy_stolen_mods_buff": {
    "name": "猎人的指导",
    "description": "你得到你所击败的稀有怪物的词缀做为己用. "
  },
  "summon_specific_monsters_cannot_die": {
    "name": "无法死亡",
    "description": ""
  },
  "phoenix_firebomb": {
    "name": "凤凰爆炎弹",
    "description": "你的火焰抗性被削弱了"
  },
  "repeated_pulse_cold": {
    "name": "憎恨精华",
    "description": "你的冰霜抗性被削弱了"
  },
  "repeated_pulse_lightning": {
    "name": "雷霆精华",
    "description": "你的闪电抗性被削弱了"
  },
  "repeated_pulse_fire": {
    "name": "愤怒精华",
    "description": "你的火焰抗性被削弱了"
  },
  "repeated_pulse_chaos": {
    "name": "凄惨精华",
    "description": "正受到持续的混沌伤害"
  },
  "essence_alternating_buffs_dodge_and_spell_dodge": {
    "name": "",
    "description": ""
  },
  "essence_alternating_buffs_reduced_damage_taken": {
    "name": "",
    "description": ""
  },
  "essence_alternating_buffs_always_crit": { "name": "", "description": "" },
  "flask_elemental_penetration": {
    "name": "",
    "description": "你的攻击穿透火焰, 冰霜, 闪电抗性"
  },
  "essence_elemental_damage_taken": { "name": "", "description": "" },
  "essence_burning_ground": { "name": "", "description": "" },
  "essence_elemental_damage_taken_granted": { "name": "", "description": "" },
  "curse_immunity": { "name": "", "description": "" },
  "essence_base_buffs_move_atack_cast_speed": { "name": "", "description": "" },
  "essence_base_buffs_damage": { "name": "", "description": "" },
  "essence_base_buffs_crit_immune": { "name": "", "description": "" },
  "permanent_debuff_on_minion_death": { "name": "", "description": "" },
  "have_blocked_attack_recently": { "name": "", "description": "" },
  "phoenix_stacking_debuff": {
    "name": "火抗上限削弱",
    "description": "你的火焰抗性上限被削弱了"
  },
  "fire_beam_damage_stacks": {
    "name": "灼热光线",
    "description":
      "你正在燃烧. 受到灼热光线附带的持续火焰伤害. 你的火焰抗性降低."
  },
  "brain_scrambler_shock_effects": { "name": "神志干扰", "description": "" },
  "razor_unique_increased_burning_damage": {
    "name": "七阳剃刀",
    "description": ""
  },
  "shaper_immune": { "name": "", "description": "" },
  "shaper_beam": { "name": "RENAME ME", "description": "DESCRIBE ME" },
  "decay": { "name": "腐蚀", "description": "你正受到混沌伤害" },
  "endurance_frenzy_charge_essence": {
    "name": "",
    "description": "获得耐力球和狂怒球"
  },
  "remnant_of_corruption_aura": {
    "name": "遗忘的腐化器皿",
    "description": "你被减速了, 并受到持续的物理伤害."
  },
  "chieftain_enrage_aura": { "name": "", "description": "" },
  "chieftain_enrage_buff": { "name": "", "description": "" },
  "rhoa_map_boss_enrage_buff": { "name": "巨喙的暴怒", "description": "" },
  "monolith_monster_freedom": { "name": "", "description": "" },
  "essence_random_charge": { "name": "", "description": "" },
  "essence_charge_max_and_duration": { "name": "", "description": "" },
  "minotaur_arctrap_debuff": {
    "name": "电弧陷阱",
    "description": "你被减速了"
  },
  "new_blade_vortex": {
    "name": "飞刃风暴",
    "description": "你被飞刃风暴的飞刃包围"
  },
  "new_blade_vortex_effect": { "name": "", "description": "" },
  "zana_immune_buff": { "name": "TEMP", "description": "" },
  "hidden_monster_disable_minions": { "name": "", "description": "" },
  "aura_movement_speed_for_spiders": { "name": "", "description": "" },
  "covered_in_spiders": {
    "name": "爬满蜘蛛",
    "description":
      "你正被蜘蛛包围! 快烧光他们! 你现在将移动更迅速但是攻击和施法速度被降低, 并且伤害减少."
  },
  "remove_covered_in_spiders": {
    "name": "火烧",
    "description": "你正在燃烧身上的蜘蛛, 你讲受到持续的火焰伤害."
  },
  "restore": {
    "name": "恢复",
    "description": "你正在持续回复生命, 魔力或能量护盾."
  },
  "alternating_buffs_item_rarity": { "name": "", "description": "" },
  "base_buffs_item_quantity": { "name": "", "description": "" },
  "unique_flask_witchfire_brew": {
    "name": "巫火之酿",
    "description": "你正造成额外的持续类伤害"
  },
  "unique_flask_dying_sun": {
    "name": "逝日",
    "description": "你的范围伤害效果增加, 并发射额外投掷物"
  },
  "atlas_lightning_golem_buff": { "name": "", "description": "" },
  "aura_atlas_gold_pile": {
    "name": "宝藏之堆",
    "description": "你的伤害得到了加强"
  },
  "hallowed_ground_boss_invulnerability": { "name": "", "description": "" },
  "elementalist_all_damage_chills": {
    "name": "冰缓汇流",
    "description": "你的伤害造成冰缓"
  },
  "elementalist_all_damage_shocks": {
    "name": "感电汇流",
    "description": "你的伤害造成感电"
  },
  "elementalist_all_damage_ignites": {
    "name": "火焰汇流",
    "description": "你的伤害造成点燃"
  },
  "elementalist_all_damage_chills_shocks_ignites": {
    "name": "元素汇流",
    "description": "你的伤害造成点燃, 冰缓, 感电"
  },
  "shaper_minions_buff": { "name": "", "description": "" },
  "map_poisoned_while_moving": { "name": "", "description": "" },
  "map_damage_taken_while_stationary": { "name": "", "description": "" },
  "map_damage_taken": { "name": "", "description": "" },
  "ground_haste": { "name": "迅捷之域", "description": "你被加速了" },
  "damage_taken_on_200_mana_spent": { "name": "", "description": "" },
  "mass_summon_ravens": { "name": "", "description": "" },
  "damage_and_damage_taken": { "name": "", "description": "" },
  "map_damage_and_damage_taken_while_stationary": {
    "name": "",
    "description": ""
  },
  "ground_tar_gold": {
    "name": "液体黄金",
    "description": "站立在液体黄金上时, 移动速度被降低"
  },
  "strongbox_enrage": { "name": "", "description": "" },
  "cover_in_ash": {
    "name": "灰烬缠身",
    "description": "你被减速了, 受到的火焰伤害增加"
  },
  "empowering_howl": { "name": "哀嚎", "description": "" },
  "new_new_blade_vortex": {
    "name": "飞刃风暴",
    "description": "你身边飞舞着飞刃"
  },
  "have_summoned_golem_in_past_8_seconds": { "name": "", "description": "" },
  "golem_summoned_in_past_8_seconds": { "name": "", "description": "" },
  "elementalist_shaper_of_desolation_cooldown": {
    "name": "",
    "description": ""
  },
  "new_blight": { "name": "枯萎", "description": "你正在受到持续混沌伤害" },
  "monster_consume_charges": { "name": "怪物吸收", "description": "" },
  "player_tencent_asset_lock_bonus": {
    "name": "游戏保护开启奖励",
    "description": "额外增加物品稀有度"
  },
  "player_tencent_no_asset_lock": {
    "name": "游戏保护未开启",
    "description": "额外物品稀有度奖励未生效(可在QQ安全中心手机版开启)"
  },
  "tencent_tas_lock": {
    "name": "安全保护状态",
    "description":
      "您正处于60秒安全保护时间或安全状态下, 暂时无法进行丢弃, 出售等敏感操作, 请等待60秒或解锁后尝试."
  },
  "blizzard_enemy": {
    "name": "暴风雪",
    "description": "在暴风雪中, 你被冰缓并且命中显著下降"
  },
  "blizzard_ally": { "name": "", "description": "" },
  "monster_convert_on_death": { "name": "", "description": "" },
  "breach_team_warp_buff": { "name": "", "description": "" },
  "breach_discharge_aura": { "name": "", "description": "" },
  "breach_discharge": { "name": "", "description": "" },
  "have_dealt_non_crit_recently": { "name": "", "description": "" },
  "have_frozen_enemy_recently": { "name": "", "description": "" },
  "number_of_shocked_enemies_killed_recently": {
    "name": "",
    "description": ""
  },
  "track_movement": { "name": "", "description": "" },
  "envy_chaos_damage": { "name": "嫉妒", "description": "附加额外混沌伤害" },
  "fire_beam_max_damage_stacks": { "name": "", "description": "" },
  "rhoa_enrage": { "name": "", "description": "" },
  "fire_beam_resistance_stacks": { "name": "", "description": "" },
  "doedre2_red_aura": {
    "name": "红色毒液",
    "description": "每层红色毒液让你增加10%受到的伤害"
  },
  "doedre2_green_aura": {
    "name": "绿色毒液",
    "description": "每层绿色毒液让你减少7%造成的伤害"
  },
  "doedre2_purple_aura": {
    "name": "紫色毒液",
    "description": "每层紫色毒液让你变慢7%"
  },
  "doedre2_red_buff": { "name": "红色增益", "description": "" },
  "doedre2_green_buff": { "name": "绿色增益", "description": "" },
  "doedre2_purple_buff": { "name": "紫色增益", "description": "" },
  "abberaths_hooves_display_buff": {
    "name": "艾贝拉斯之怒",
    "description": "每踏下一步都造成一次小爆炸, 对周围造成火焰伤害"
  },
  "avarius_divine_beam_damage": {
    "name": "神圣光辉",
    "description": "你正在受到持续的火焰伤害."
  },
  "avarius_divine_beam_debuff": {
    "name": "神圣光辉",
    "description": "被光束覆盖的时间越长, 你受到的伤害将逐步提升."
  },
  "avarius_statue_buff": { "name": "", "description": "" },
  "spider_god_spiders": {
    "name": "蛛网束缚",
    "description": "你被蛛网缠住了, 移动速度下降."
  },
  "number_of_chests_opened_recently": { "name": "", "description": "" },
  "have_shattered_recently": { "name": "", "description": "" },
  "additional_ignite": { "name": "点燃", "description": "你被点燃了. " },
  "unique_flask_the_basics": { "name": "基础", "description": "" },
  "classic_prophecy_quantity": { "name": "预言数量", "description": "" },
  "tukohama_shield": { "name": "", "description": "" },
  "ground_tar_net": { "name": "投网", "description": "你的移动速度下降了." },
  "offering_blood": {
    "name": "血脉奉献",
    "description": "你的伤害增加并在回复生命值。"
  },
  "have_blocked_spell_recently": { "name": "", "description": "" },
  "have_used_a_fire_skill_recently": { "name": "", "description": "" },
  "brutus_empowered": { "name": "", "description": "" },
  "unique_victarios_flight_movement_velocity": {
    "name": "维多里奥的飞升",
    "description": "你和你友军的移动速度提升"
  },
  "intimidated_aura": { "name": "威吓", "description": "你受到了威吓" },
  "beyond_host": { "name": "", "description": "" },
  "brine_king_tide": {
    "name": "潮汐之力",
    "description": "你受到潮汐影响, 动作变慢并受到持续的冰霜伤害."
  },
  "energy_shield_has_started_recharging_recently": {
    "name": "",
    "description": ""
  },
  "ground_devouring_darkness": {
    "name": "吞噬黑暗",
    "description": "你正在受到持续的物理伤害"
  },
  "have_stopped_taking_damage_over_time_recently": {
    "name": "",
    "description": ""
  },
  "have_been_frozen_recently": { "name": "", "description": "" },
  "have_been_stunned_recently": { "name": "", "description": "" },
  "tukohama_god_stationary_buff": { "name": "", "description": "" },
  "ryslatha_god_life_flask_charges_gain": { "name": "", "description": "" },
  "tangmazu_god_curses_have_no_effect_on_you_cooldown": {
    "name": "",
    "description": ""
  },
  "curses_have_no_effect_on_you": { "name": "", "description": "" },
  "infested": { "name": "被感染", "description": "你的药水能量正在逐渐流失" },
  "despair_bear_buff": {
    "name": "绝望",
    "description": "你被减速了, 并且照亮范围变小."
  },
  "fearless": {
    "name": "无畏",
    "description": "无畏状态下不会死亡. 当靠近恐惧元素时会摧毁他们."
  },
  "frog_orb_aura": {
    "name": "畏惧",
    "description": "周围的每一个恐惧元素会使你受到额外的持续冰霜伤害."
  },
  "frog_orb_aura_minions": {
    "name": "畏惧",
    "description": "周围的每一个恐惧元素会使你受到额外的持续冰霜伤害."
  },
  "water_orb_aura": {
    "name": "畏惧",
    "description": "你身边的每一层畏惧的表象会使你受到持续的冰霜伤害。"
  },
  "stolen_mods_inspired_learning": {
    "name": "求知的热情",
    "description": "你得到你击败的稀有怪物的词缀并拿为己用"
  },
  "stolen_mods_leaguestone": {
    "name": "复仇赛季石",
    "description": "你得到一些你击败的稀有怪物的词缀并拿为己用"
  },
  "abberath_minion_buff": { "name": "", "description": "" },
  "herald_of_ash_burning": {
    "name": "燃烧",
    "description": "你正受到敌人灰烬之捷的影响, 受到持续火焰伤害"
  },
  "have_shocked_recently": { "name": "", "description": "" },
  "kitava_swipe_debuff": { "name": "", "description": "" },
  "despair_bear_slow": { "name": "", "description": "" },
  "have_used_movement_skill_recently": { "name": "", "description": "" },
  "ascendant_chaos_resistance": { "name": "", "description": "" },
  "ascendant_block_chance": { "name": "", "description": "" },
  "ascendant_attack_cast_movement_speed": { "name": "", "description": "" },
  "have_placed_trap_or_mine_recently": { "name": "", "description": "" },
  "ground_despair_geyser": {
    "name": "绝望之地",
    "description": "你正在受到持续的物理伤害, 并且移动速度降低."
  },
  "support_maimed_enemies_damage_taken": { "name": "", "description": "" },
  "have_used_a_cold_skill_recently": { "name": "", "description": "" },
  "attack_speed_debuff_from_hitting_enemy_recently": {
    "name": "",
    "description": ""
  },
  "yugul_hidden_monster": { "name": "", "description": "" },
  "ground_maelstrom_chill_lunaris": {
    "name": "月影风暴",
    "description": "正受到来自月影女神的伤害"
  },
  "silver_orb_aggressive": { "name": "", "description": "" },
  "ground_sandstorm": {
    "name": "格鲁坎的沙暴",
    "description": "你正受到持续的物理伤害"
  },
  "number_of_nearby_enemies": { "name": "", "description": "" },
  "ralakesh_buff": { "name": "", "description": "" },
  "plague": { "name": "疫源", "description": "你正受到持续的混沌伤害" },
  "accelerate": { "name": "", "description": "" },
  "arcane_surge": {
    "name": "秘术增强",
    "description": "你额外增加法术总伤害, 增加施法速度和魔力回复速度"
  },
  "mana_gained_from_hit_damage": { "name": "", "description": "" },
  "lightning_thorns_cold": {
    "name": "冰霜荆棘",
    "description": "被击中时反射冰霜伤害"
  },
  "blight_hinder_chaos_damage_taken": { "name": "", "description": "" },
  "moontouched_buff": { "name": "", "description": "" },
  "innervate_support": {
    "name": "闪电支配",
    "description": "你附加了闪电伤害"
  },
  "blackguardzombie_enrage": { "name": "", "description": "" },
  "basilisk_slow": { "name": "石化凝视", "description": "你正在逐渐被石化。" },
  "basilisk_gaze": { "name": "", "description": "" },
  "bleeding_stack": {
    "name": "流血",
    "description": "你正在流血, 受到持续物理伤害"
  },
  "ruthless_big_hit_counter": { "name": "", "description": "" },
  "boulderdash_enrage": { "name": "巨石之怒", "description": "" },
  "doedre_pillar_red_aura": {
    "name": "德瑞之罪",
    "description": "每层让你增加6%受到的伤害"
  },
  "doedre_pillar_green_aura": {
    "name": "德瑞之畏",
    "description": "每层让你和你的召唤生物减少7%造成的伤害"
  },
  "doedre_pillar_purple_aura": {
    "name": "德瑞之苦",
    "description": "每层让你变慢5%"
  },
  "general_adus_supercharged": { "name": "", "description": "" },
  "monster_temporary_additional_projectiles": { "name": "", "description": "" },
  "intimidated_aura_rhoa": {
    "name": "威吓",
    "description": "你受到额外10%伤害"
  },
  "arcane_surge_mana_spent": { "name": "", "description": "" },
  "darktongue_kiss": {
    "name": "暗语之吻",
    "description": "你将持续受到混沌伤害"
  },
  "harbinger_minion_new": { "name": "", "description": "" },
  "have_blocked_a_stun_recently": { "name": "", "description": "" },
  "void_gaze": { "name": "虚空凝视", "description": "你的混沌抗性降低" },
  "charged_dash_chance_to_dodge": { "name": "", "description": "" },
  "kitava_heart_damage_taken": { "name": "", "description": "" },
  "abyss_monsters_damage_taken": { "name": "", "description": "" },
  "harbinger_action_speed_aura": {
    "name": "流逝之时",
    "description": "在你的周围时间流动的更快"
  },
  "harbinger_channel_buff": {
    "name": "不屈之志",
    "description": "你无法被晕眩, 不受异常状态影响, 并且受到的伤害减少"
  },
  "harbinger_projectile_buff": {
    "name": "爆裂之射",
    "description": "你的投射物有额外属性"
  },
  "harbinger_damage_buff": {
    "name": "圣恶之喻",
    "description": "你的伤害, 攻击速度, 移动速度提升, 并且受到的伤害减少"
  },
  "harbinger_minion_buff": { "name": "", "description": "" },
  "pantheon_brine_king_stun_immunity": { "name": "", "description": "" },
  "harbinger_cold_beacon": { "name": "", "description": "" },
  "harbinger_tiger_enrage": { "name": "", "description": "" },
  "harbinger_mortar_buff": { "name": "", "description": "" },
  "power_charge_on_mana_spent": { "name": "", "description": "" },
  "caustic_cloud_trail": {
    "name": "腐蚀之击",
    "description": "你正在当前位置召唤腐蚀毒云。保持移动可以移除该减益效果。"
  },
  "quicksand_aura": { "name": "", "description": "" },
  "quicksand_buff": { "name": "", "description": "" },
  "malachais_endurance": {
    "name": "马拉凯之耐",
    "description": "击败时有20%几率获得一个耐力球"
  },
  "malachais_frenzy": {
    "name": "马拉凯之狂",
    "description": "击败时有20%几率获得一个狂怒球"
  },
  "malachais_power": {
    "name": "马拉凯之暴",
    "description": "击败时有20%几率获得一个暴击球"
  },
  "thaumaturgy_rotation": { "name": "", "description": "" },
  "ankh_of_eternity_enrage": { "name": "", "description": "" },
  "gain_random_charges_while_stationary": { "name": "", "description": "" },
  "quicksand_display_buff": {
    "name": "流沙",
    "description": "你正在被流沙减速"
  },
  "unique_flask_gorgon_poison": {
    "name": "克拉里多之名",
    "description":
      "你正在受到混沌伤害，并处于完美痛苦状态。你有几率使敌人中毒并增加其中毒持续时间。你的暴击不会造成暴击伤害加成。"
  },
  "spectral_spinning_weapon": { "name": "", "description": "" },
  "unique_flask_shakari_increased_speed": {
    "name": "沙卡丽之沙",
    "description": ""
  },
  "unique_flask_shakari_reduced_speed_per_second": {
    "name": "",
    "description": ""
  },
  "have_been_damaged_by_hit_recently": { "name": "", "description": "" },
  "have_used_a_minion_skill_recently": { "name": "", "description": "" },
  "has_player_minion_been_killed_recently": { "name": "", "description": "" },
  "minion_has_killed_enemy_recently": { "name": "", "description": "" },
  "aegis_fire_buff": {
    "name": "烈焰守护",
    "description":
      "被火焰伤害击中时先消耗烈焰守护，之后才消耗生命或能量护盾。该守护在一定时间未受到火焰伤害后会再次恢复满值。"
  },
  "aegis_cold_buff": {
    "name": "凝冰守护",
    "description":
      "被冰霜伤害击中时先消耗凝冰守护，之后才消耗生命或能量护盾。该守护在一定时间未受到冰霜伤害后会再次恢复满值。"
  },
  "aegis_elemental_buff": {
    "name": "元素守护",
    "description":
      "被元素伤害击中时先消耗元素守护，之后才消耗生命或能量护盾。该守护在一定时间未受到元素伤害后会再次恢复满值。"
  },
  "aegis_fire_depleted": {
    "name": "烈焰守护",
    "description":
      "该守护已被消耗光，一段时间内未受到火焰伤害将再次充满该守护。"
  },
  "aegis_cold_depleted": {
    "name": "凝冰守护",
    "description":
      "该守护已被消耗光，一段时间内未受到冰霜伤害将再次充满该守护。"
  },
  "aegis_elemental_depleted": {
    "name": "元素守护",
    "description":
      "该守护已被消耗光，一段时间内未受到元素伤害将再次充满该守护。"
  },
  "aegis_fire_persist_value": { "name": "", "description": "" },
  "aegis_cold_persist_value": { "name": "", "description": "" },
  "aegis_elemental_persist_value": { "name": "", "description": "" },
  "fire_impurity_buff": {
    "name": "不净之火",
    "description": "免疫点燃并减少受到的火焰伤害。"
  },
  "cold_impurity_buff": {
    "name": "不净之冰",
    "description": "免疫冻结并减少受到的冰霜伤害。"
  },
  "lightning_impurity_buff": {
    "name": "不净之雷",
    "description": "免疫感电并减少受到的闪电伤害。"
  },
  "storm_barrier_support": {
    "name": "风暴屏障",
    "description":
      "你正在持续吟唱并受到风暴屏障的保护，被击中时受到的闪电和物理伤害减少。"
  },
  "critical_strike_chance_on_mana_spent": { "name": "", "description": "" },
  "critical_strike_chance_unique": {
    "name": "卡莉莎的优雅之影",
    "description": "你有更高的几率造成暴击。"
  },
  "her_embrace_unique": {
    "name": "女神之拥",
    "description":
      "无法被晕眩\n获得等同剑物理伤害123%的额外火焰伤害\n不受燃烧地面影响\n免疫冰冻，冰缓和点燃\n增加 20% 攻击，施法和移动速度"
  },
  "grasping_vines_aura": {
    "name": "缓速藤蔓",
    "description": "静止不动时你将被减速。"
  },
  "grasping_vines_buff": {
    "name": "缓速藤蔓",
    "description": "你被缓速藤蔓减速了。移动以挣脱藤蔓。"
  },
  "disable_light": { "name": "", "description": "" },
  "tentacle_fiend_aura": {
    "name": "恶魔之触",
    "description": "你被减速了并且造成的伤害减少。"
  },
  "tentacle_fiend_aura_monster": {
    "name": "恶魔之触",
    "description": "受到附近恶魔之触的影响，你被减速了并且造成的伤害减少。"
  },
  "elder_siphon_debuff": {
    "name": "裂界之荼",
    "description": "你正在受到持续的物理伤害。"
  },
  "elder_siphon_buff": { "name": "", "description": "" },
  "elder_siphon_slow": { "name": "裂界之缓", "description": "你被减速了。" },
  "elder_siphon_immobilise": {
    "name": "裂界之固",
    "description": "你无法移动。"
  },
  "ailments_types_grant_damage_taken_child_buff_shock": {
    "name": "",
    "description": ""
  },
  "ailments_types_grant_damage_taken_child_buff_freeze": {
    "name": "",
    "description": ""
  },
  "ailments_types_grant_damage_taken_child_buff_chill": {
    "name": "",
    "description": ""
  },
  "ailments_types_grant_damage_taken_child_buff_ignite": {
    "name": "",
    "description": ""
  },
  "ailments_types_grant_damage_taken_child_buff_bleeding": {
    "name": "",
    "description": ""
  },
  "ailments_types_grant_damage_taken_child_buff_poison": {
    "name": "",
    "description": ""
  },
  "stolen_mods_elder_stat": {
    "name": "能力窃取",
    "description": "你获得了被击败稀有怪物的部分能力。"
  },
  "reduced_evasion_from_hit": { "name": "", "description": "" },
  "iron_reflexes_every_16_sec": { "name": "", "description": "" },
  "iron_reflexes_from_unique": {
    "name": "霸体",
    "description": "你获得了霸体。"
  },
  "have_stunned_an_enemy_recently": { "name": "", "description": "" },
  "gain_endurance_charges_while_stationary": { "name": "", "description": "" },
  "death_walk_display_buff": {
    "name": "泯灭之舞",
    "description": "移动时会摧毁附近的灵柩并造成火焰范围伤害。"
  },
  "mother_of_flames_daemon_debuff": {
    "name": "发射熔岩之核",
    "description": ""
  },
  "elemental_overload_every_16_sec": { "name": "", "description": "" },
  "elemental_overload_from_unique": {
    "name": "元素超载",
    "description": "你获得了元素超载。"
  },
  "avatar_of_fire_every_8_sec": { "name": "", "description": "" },
  "avatar_of_fire_from_unique": {
    "name": "火之化身",
    "description": "你获得了火之化身。"
  },
  "physical_reflect_mortar_mod": {
    "name": "物理棘刺",
    "description": "在你受到物理伤害时发射一个造成物理伤害的投射物"
  },
  "elemental_reflect_mortar_mod": {
    "name": "元素棘刺",
    "description": "在你受到元素伤害时发射一个造成元素伤害的投射物"
  },
  "disable_rarity_epk": { "name": "", "description": "" },
  "curse_chaos_weakness": {
    "name": "绝望",
    "description":
      "你被诅咒了，你的混沌抗性降低，将受到更多的持续伤害，被击中时将受到额外混沌伤害。"
  },
  "mirage_archer_visual_buff": { "name": "", "description": "" },
  "shade_form": {
    "name": "暗影姿态",
    "description": "你对物理伤害免疫并且很难被发现。"
  },
  "lich_crystal_damage_reduction": { "name": "", "description": "" },
  "petrification_statue_gaze": {
    "name": "石化",
    "description": "你被石化了。"
  },
  "elder_ground_spores": {
    "name": "裂界之殇",
    "description": "你处于裂界之殇内，正在受到物理伤害。"
  },
  "kitava_visual_display_buff": { "name": "", "description": "" },
  "elder_tentacle_portal_no_revive": { "name": "", "description": "" },
  "minions_no_drops_or_experience": { "name": "", "description": "" },
  "zana_dont_hurt_me": {
    "name": "札娜的庇护",
    "description": "你正在被札娜庇护。你不会受到伤害也不会死亡。"
  },
  "skill_interruption": { "name": "", "description": "" },
  "total_mana_spent_recently": { "name": "", "description": "" },
  "have_used_a_skill_recently": { "name": "", "description": "" },
  "gain_void_arrows": { "name": "", "description": "" }
}
