{
  "0": { "description": "Mate outro jogador em uma partida 1v1." },
  "1": { "description": "Vença uma partida 1v1." },
  "2": {
    "description": "Vença uma rodada de uma partida 1v1 sem usar nenhum frasco."
  },
  "3": {
    "description":
      "Mate outro jogador em uma partida 1v1 %1% segundos após o início de uma rodada."
  },
  "4": { "description": "Vença uma partida 1v1 como %1%." },
  "5": { "description": "Vença uma partida 1v1 como %1%." },
  "6": { "description": "Mate outro jogador durante uma partida 3v3." },
  "7": { "description": "Vença uma partida 3v3." },
  "8": {
    "description":
      "Abata todos os jogadores inimigos em uma única rodada durante uma partida 3v3."
  },
  "9": {
    "description":
      "Abata outro jogador em uma partida 3v3 %1% segundos após o início de uma rodada."
  },
  "10": { "description": "Vença uma partida 3v3 como %1%." },
  "11": { "description": "Vença uma partida 3v3 como %1%." },
  "12": { "description": "Abata outro jogador durante uma partida de PaB." },
  "13": { "description": "Vença uma partida de PaB." },
  "14": { "description": "Pegue uma bandeira durante uma partida de PaB." },
  "15": {
    "description": "Devolva a bandeira derrubada durante uma partida de PaB."
  },
  "16": {
    "description":
      "Abata outro jogador que estiver carregando a bandeira durante uma partida de PaB."
  },
  "17": { "description": "Vença uma partida de PaB como %1%." },
  "18": { "description": "Vença uma partida de PaB como %1%." },
  "19": { "description": "Abata outro jogador na Arena de Sarn." },
  "20": {
    "description": "Sobreviva por %1% segundos na Arena de Sarn sem morrer."
  },
  "21": {
    "description": "Abata %1% outros jogadores na Arena de Sarn sem morrer."
  },
  "22": {
    "description":
      "Abata %1% outros jogadores em %2% segundos na Arena de Sarn."
  }
}
