{
  "Metadata/NPC/Act1/Tarkleigh": { "name": "Tarkleigh", "shortname": "" },
  "Metadata/NPC/Act1/Nessa": { "name": "Nessa", "shortname": "" },
  "Metadata/NPC/Act1/Bestel": { "name": "Bestel", "shortname": "" },
  "Metadata/NPC/Act1/Doorman": { "name": "Porteiro", "shortname": "" },
  "Metadata/NPC/Act1/Fairgraves": {
    "name": "Capitão Fairgraves",
    "shortname": "Fairgraves"
  },
  "Metadata/NPC/Act1/WoundedExile": {
    "name": "Exilado Moribundo",
    "shortname": ""
  },
  "Metadata/NPC/Act1/Brutus": {
    "name": "Brutus, o Carcereiro",
    "shortname": "Brutus"
  },
  "Metadata/NPC/Act1/Merveil": { "name": "Merveil", "shortname": "" },
  "Metadata/NPC/Act2/Eramir": { "name": "Eramir", "shortname": "" },
  "Metadata/NPC/Act2/Yeena": { "name": "Yeena", "shortname": "" },
  "Metadata/NPC/Act2/Greust": { "name": "Greust", "shortname": "" },
  "Metadata/NPC/Act2/Silk": { "name": "Silk", "shortname": "" },
  "Metadata/Monsters/BanditLeaderInt/BanditLeaderInt": {
    "name": "Alira",
    "shortname": ""
  },
  "Metadata/Monsters/BanditLeaderDexInt/BanditLeaderDexInt": {
    "name": "Kraityn",
    "shortname": ""
  },
  "Metadata/Monsters/BanditLeaderStrDex/BanditLeaderStrDex": {
    "name": "Oak",
    "shortname": ""
  },
  "Metadata/NPC/Act3/Hargan": { "name": "Hargan", "shortname": "" },
  "Metadata/NPC/Act3/Dialla": {
    "name": "Senhora Dialla",
    "shortname": "Dialla"
  },
  "Metadata/NPC/Act3/DiallaTower": {
    "name": "Senhora Dialla",
    "shortname": "Dialla"
  },
  "Metadata/NPC/Act3/Maramoa": { "name": "Maramoa", "shortname": "" },
  "Metadata/NPC/Act3/Grigor": { "name": "Grigor", "shortname": "" },
  "Metadata/NPC/Act3/ClarissaTown": { "name": "Clarissa", "shortname": "" },
  "Metadata/NPC/Act3/ClarissaSlums": { "name": "Clarissa", "shortname": "" },
  "Metadata/NPC/Info/PrisonDiary": {
    "name": "Diário de Shavronne",
    "shortname": ""
  },
  "Metadata/NPC/Act2/HelenaTown": { "name": "Helena", "shortname": "" },
  "Metadata/NPC/Act2/HelenaSins": { "name": "Helena", "shortname": "" },
  "Metadata/NPC/Act3/Siosa": { "name": "Siosa", "shortname": "" },
  "Metadata/NPC/Act3/Fairgraves": {
    "name": "Capitão Fairgraves",
    "shortname": "Fairgraves"
  },
  "Metadata/NPC/Piety": { "name": "Piety", "shortname": "" },
  "Metadata/NPC/Gravicius": { "name": "Gravicius", "shortname": "" },
  "Metadata/NPC/Dominus": { "name": "Dominus", "shortname": "" },
  "Metadata/NPC/Act4/Kaom": { "name": "Rei Kaom", "shortname": "Kaom" },
  "Metadata/NPC/Act4/Maligaro": {
    "name": "Maligaro, o Inquisidor",
    "shortname": "Maligaro"
  },
  "Metadata/NPC/Act4/Shavronne": { "name": "Shavronne", "shortname": "" },
  "Metadata/NPC/Act4/Malachai": { "name": "Malachai", "shortname": "" },
  "Metadata/NPC/Act4/Daresso": { "name": "Daresso", "shortname": "" },
  "Metadata/NPC/Oba": { "name": "Oba", "shortname": "" },
  "Metadata/NPC/Info/ArteriLetter": {
    "name": "Carta de Arteri",
    "shortname": ""
  },
  "Metadata/NPC/Info/BeachEncampmentNotes": {
    "name": "Cartas de Exílio",
    "shortname": ""
  },
  "Metadata/NPC/Info/Karui/Stone1": {
    "name": "Escultura Castigada",
    "shortname": ""
  },
  "Metadata/NPC/Info/Karui/Stone2": {
    "name": "Escultura Castigada",
    "shortname": ""
  },
  "Metadata/NPC/Info/Karui/Stone3": {
    "name": "Escultura Castigada",
    "shortname": ""
  },
  "Metadata/NPC/Info/Karui/Stone4": {
    "name": "Escultura Castigada",
    "shortname": ""
  },
  "Metadata/NPC/Info/Karui/Stone5": {
    "name": "Escultura Castigada",
    "shortname": ""
  },
  "Metadata/NPC/Info/Karui/Stone6": {
    "name": "Escultura Castigada",
    "shortname": ""
  },
  "Metadata/NPC/Info/Karui/Stone7": {
    "name": "Escultura Castigada",
    "shortname": ""
  },
  "Metadata/NPC/Info/Victario/GraffitiIntro": {
    "name": "Pichação Antiga",
    "shortname": ""
  },
  "Metadata/NPC/Info/Victario/GraffitiSlum": {
    "name": "Pichação Antiga",
    "shortname": ""
  },
  "Metadata/NPC/Info/Victario/GraffitiWarehouse": {
    "name": "Pichação Antiga",
    "shortname": ""
  },
  "Metadata/NPC/Info/Victario/GraffitiBattlefront": {
    "name": "Pichação Antiga",
    "shortname": ""
  },
  "Metadata/NPC/Info/Victario/GraffitiDocks": {
    "name": "Pichação Antiga",
    "shortname": ""
  },
  "Metadata/NPC/Info/Victario/GraffitiChurch": {
    "name": "Pichação Antiga",
    "shortname": ""
  },
  "Metadata/NPC/Info/Victario/Notebook": {
    "name": "Caderno Antigo",
    "shortname": ""
  },
  "Metadata/NPC/Info/MerveilSkin": {
    "name": "Pele de Pescador",
    "shortname": ""
  },
  "Metadata/NPC/Info/MerveilDiary": { "name": "Diário Úmido", "shortname": "" },
  "Metadata/NPC/Act3/Scion": { "name": "Herdeira", "shortname": "" },
  "Metadata/NPC/Info/MapDevice": {
    "name": "Dispositivo de Devaneio",
    "shortname": ""
  },
  "Metadata/NPC/Info/MapDeviceOld": {
    "name": "Antigo Dispositivo de Devaneio",
    "shortname": ""
  },
  "Metadata/NPC/Info/GemCart": {
    "name": "Dispositivo de Transmutação",
    "shortname": ""
  },
  "Metadata/NPC/Info/LibraryGaribaldi1": {
    "name": "As Crônicas da Pureza",
    "shortname": ""
  },
  "Metadata/NPC/Info/LibraryGaribaldi2": {
    "name": "As Crônicas da Pureza",
    "shortname": ""
  },
  "Metadata/NPC/Info/LibraryGaribaldi3": {
    "name": "As Crônicas da Pureza",
    "shortname": ""
  },
  "Metadata/NPC/Info/LibraryGaribaldi4": {
    "name": "As Crônicas da Pureza",
    "shortname": ""
  },
  "Metadata/NPC/Info/LibraryGaribaldi5": {
    "name": "As Crônicas da Pureza",
    "shortname": ""
  },
  "Metadata/NPC/Info/LibraryGaribaldi6": {
    "name": "As Crônicas da Pureza",
    "shortname": ""
  },
  "Metadata/NPC/Info/LibraryVictario1": {
    "name": "Textos do Victario",
    "shortname": ""
  },
  "Metadata/NPC/Info/LibraryVictario2": {
    "name": "Textos do Victario",
    "shortname": ""
  },
  "Metadata/NPC/Info/LibraryVictario3": {
    "name": "Textos do Victario",
    "shortname": ""
  },
  "Metadata/NPC/Info/LibraryVictario4": {
    "name": "Textos do Victario",
    "shortname": ""
  },
  "Metadata/NPC/Info/LibraryMilitary1": {
    "name": "Os Antigos",
    "shortname": ""
  },
  "Metadata/NPC/Info/LibraryMilitary2": {
    "name": "Os Antigos",
    "shortname": ""
  },
  "Metadata/NPC/Info/LibraryMilitary3": {
    "name": "Os Antigos",
    "shortname": ""
  },
  "Metadata/NPC/Info/LibraryMilitary4": {
    "name": "Os Antigos",
    "shortname": ""
  },
  "Metadata/NPC/Info/LibraryMilitary5": {
    "name": "Os Antigos",
    "shortname": ""
  },
  "Metadata/NPC/Info/LibraryMilitary6": {
    "name": "Os Antigos",
    "shortname": ""
  },
  "Metadata/NPC/Info/LibraryMilitary7": {
    "name": "Os Antigos",
    "shortname": ""
  },
  "Metadata/NPC/Info/MalachaiStatue": { "name": "Placa", "shortname": "" },
  "Metadata/NPC/Info/CrossroadsLoreChapel": {
    "name": "Gravuras na Madeira IV",
    "shortname": ""
  },
  "Metadata/NPC/Info/CrossroadsLoreWindmill": {
    "name": "Gravuras na Madeira III",
    "shortname": ""
  },
  "Metadata/NPC/Info/CrossroadsLoreVilla": {
    "name": "Gravuras na Madeira I",
    "shortname": ""
  },
  "Metadata/NPC/Info/CrossroadsLoreVilla2": {
    "name": "Gravuras na Madeira II",
    "shortname": ""
  },
  "Metadata/NPC/Info/HighgateNote": { "name": "Nota", "shortname": "" },
  "Metadata/NPC/Info/GeofriPlaque": { "name": "Placa", "shortname": "" },
  "Metadata/NPC/Info/TallStones": { "name": "Proclamação", "shortname": "" },
  "Metadata/NPC/Info/DaressoStatue1": { "name": "Placa", "shortname": "" },
  "Metadata/NPC/Info/DaressoStatue2": { "name": "Placa", "shortname": "" },
  "Metadata/NPC/Info/DaressoStatue3": { "name": "Placa", "shortname": "" },
  "Metadata/NPC/Info/KaomCarving1": {
    "name": "Escultura Castigada",
    "shortname": ""
  },
  "Metadata/NPC/Info/KaomCarving2": {
    "name": "Escultura Castigada",
    "shortname": ""
  },
  "Metadata/NPC/Info/KaomCarving3": {
    "name": "Escultura Castigada",
    "shortname": ""
  },
  "Metadata/NPC/Info/KaomCarving4": {
    "name": "Escultura Castigada",
    "shortname": ""
  },
  "Metadata/Chests/DescentChests/DescentChestNPC1": {
    "name": "Baú 1",
    "shortname": ""
  },
  "Metadata/Chests/DescentChests/DescentChestNPC2": {
    "name": "Baú 2",
    "shortname": ""
  },
  "Metadata/NPC/Info/LioneyesStandard": {
    "name": "Estandarte de Lioneye",
    "shortname": ""
  },
  "Metadata/NPC/Info/ResonatorInstructions": {
    "name": "Instruções do Ressonador",
    "shortname": ""
  },
  "Metadata/NPC/Info/VollBookStand": {
    "name": "Confissão de Voll",
    "shortname": ""
  },
  "Metadata/NPC/Info/MalachaiNotebook": {
    "name": "Caderno de Malachai",
    "shortname": ""
  },
  "Metadata/NPC/Info/MalachaiSkinscrawl": {
    "name": "Dedicação de Malachai",
    "shortname": ""
  },
  "Metadata/NPC/Act4/Kira": { "name": "Kira", "shortname": "" },
  "Metadata/NPC/Act4/Oyun": { "name": "Oyun", "shortname": "" },
  "Metadata/NPC/Act4/PetarusVanja": {
    "name": "Petarus e Vanja",
    "shortname": ""
  },
  "Metadata/NPC/Act4/DiallaAqueduct": {
    "name": "Senhora Dialla",
    "shortname": "Dialla"
  },
  "Metadata/NPC/Act4/DiallaTown": {
    "name": "Senhora Dialla",
    "shortname": "Dialla"
  },
  "Metadata/NPC/Act4/DiallaRapture": {
    "name": "Senhora Dialla",
    "shortname": "Dialla"
  },
  "Metadata/NPC/Act4/DiallaTownWithered": {
    "name": "Dialla",
    "shortname": "Dialla"
  },
  "Metadata/NPC/Act4/PietyHarvest": { "name": "Piety", "shortname": "Piety" },
  "Metadata/NPC/Act4/PietyBelly": { "name": "Piety", "shortname": "Piety" },
  "Metadata/NPC/Act4/Tasuni": { "name": "Tasuni", "shortname": "" },
  "Metadata/NPC/Missions/Dex": {
    "name": "Tora, Mestre da Caça",
    "shortname": "Tora"
  },
  "Metadata/NPC/Missions/Int": {
    "name": "Catarina, Mestre dos Mortos",
    "shortname": "Catarina"
  },
  "Metadata/NPC/Missions/Str": {
    "name": "Haku, Mestre das Armaduras",
    "shortname": "Haku"
  },
  "Metadata/NPC/Missions/DexInt": {
    "name": "Vorici, Mestre Assassino",
    "shortname": "Vorici"
  },
  "Metadata/NPC/Missions/StrDex": {
    "name": "Vagan, Mestre das Armas",
    "shortname": "Vagan"
  },
  "Metadata/NPC/Missions/StrInt": {
    "name": "Elreon, Mestre do Conhecimento",
    "shortname": "Elreon"
  },
  "Metadata/NPC/Missions/StrDexInt": {
    "name": "Zana, Mestre da Cartografia",
    "shortname": "Zana"
  },
  "Metadata/NPC/Missions/PvP": {
    "name": "Leo, Mestre da Arena",
    "shortname": "Leo"
  },
  "Metadata/NPC/Missions/Wild/Dex": {
    "name": "Tora, Mestre da Caça",
    "shortname": "Tora"
  },
  "Metadata/NPC/Missions/Wild/Int": {
    "name": "Catarina, Mestre dos Mortos",
    "shortname": "Catarina"
  },
  "Metadata/NPC/Missions/Wild/Str": {
    "name": "Haku, Mestre das Armaduras",
    "shortname": "Haku"
  },
  "Metadata/NPC/Missions/Wild/DexInt": {
    "name": "Vorici, Mestre Assassino",
    "shortname": "Vorici"
  },
  "Metadata/NPC/Missions/Wild/StrDex": {
    "name": "Vagan, Mestre das Armas",
    "shortname": "Vagan"
  },
  "Metadata/NPC/Missions/Wild/StrInt": {
    "name": "Elreon, Mestre do Conhecimento",
    "shortname": "Elreon"
  },
  "Metadata/NPC/Missions/Wild/StrDexInt": {
    "name": "Zana, Mestre da Cartografia",
    "shortname": "Zana"
  },
  "Metadata/NPC/Missions/Wild/Fish": {
    "name": "Krillson, Mestre Pescador",
    "shortname": "Krillson"
  },
  "Metadata/NPC/Missions/Hideout/Dex": {
    "name": "Tora, Mestre da Caça",
    "shortname": "Tora"
  },
  "Metadata/NPC/Missions/Hideout/DexDemo": {
    "name": "Tora, Mestre da Caça",
    "shortname": "Tora"
  },
  "Metadata/NPC/Missions/Hideout/Int": {
    "name": "Catarina, Mestre dos Mortos",
    "shortname": "Catarina"
  },
  "Metadata/NPC/Missions/Hideout/IntDemo": {
    "name": "Catarina, Mestre dos Mortos",
    "shortname": "Catarina"
  },
  "Metadata/NPC/Missions/Hideout/Str": {
    "name": "Haku, Mestre das Armaduras",
    "shortname": "Haku"
  },
  "Metadata/NPC/Missions/Hideout/StrDemo": {
    "name": "Haku, Mestre das Armaduras",
    "shortname": "Haku"
  },
  "Metadata/NPC/Missions/Hideout/DexInt": {
    "name": "Vorici, Mestre Assassino",
    "shortname": "Vorici"
  },
  "Metadata/NPC/Missions/Hideout/DexIntDemo": {
    "name": "Vorici, Mestre Assassino",
    "shortname": "Vorici"
  },
  "Metadata/NPC/Missions/Hideout/StrDex": {
    "name": "Vagan, Mestre das Armas",
    "shortname": "Vagan"
  },
  "Metadata/NPC/Missions/Hideout/StrDexDemo": {
    "name": "Vagan, Mestre das Armas",
    "shortname": "Vagan"
  },
  "Metadata/NPC/Missions/Hideout/StrInt": {
    "name": "Elreon, Mestre do Conhecimento",
    "shortname": "Elreon"
  },
  "Metadata/NPC/Missions/Hideout/StrIntDemo": {
    "name": "Elreon, Mestre do Conhecimento",
    "shortname": "Elreon"
  },
  "Metadata/NPC/Missions/Hideout/StrDexInt": {
    "name": "Zana, Mestre da Cartografia",
    "shortname": "Zana"
  },
  "Metadata/NPC/Missions/Hideout/StrDexIntDemo": {
    "name": "Zana, Mestre da Cartografia",
    "shortname": "Zana"
  },
  "Metadata/NPC/Missions/Hideout/PvP": {
    "name": "Leo, Mestre da Arena",
    "shortname": "Leo"
  },
  "Metadata/NPC/Missions/Hideout/PvPDemo": {
    "name": "Leo, Mestre da Arena",
    "shortname": "Leo"
  },
  "Metadata/NPC/Labyrinth/LabyrinthTrialGlyphPrison": {
    "name": "Monografia de Bronze",
    "shortname": ""
  },
  "Metadata/NPC/Labyrinth/LabyrinthTrialGlyphSins": {
    "name": "Monografia de Bronze",
    "shortname": ""
  },
  "Metadata/NPC/Labyrinth/LabyrinthTrialGlyphChurch": {
    "name": "Monografia de Bronze",
    "shortname": ""
  },
  "Metadata/NPC/Labyrinth/LabyrinthTrialGlyphCrematorium": {
    "name": "Monografia de Bronze",
    "shortname": ""
  },
  "Metadata/NPC/Labyrinth/LabyrinthTrialGlyphHedge": {
    "name": "Monografia de Bronze",
    "shortname": ""
  },
  "Metadata/NPC/Labyrinth/LabyrinthTrialGlyphCatacombs": {
    "name": "Monografia de Bronze",
    "shortname": ""
  },
  "Metadata/NPC/Labyrinth/LabyrinthGlyph0": {
    "name": "Placa de Bronze",
    "shortname": ""
  },
  "Metadata/NPC/Labyrinth/LabyrinthGlyph1": {
    "name": "Inscrição de Bronze",
    "shortname": ""
  },
  "Metadata/NPC/Labyrinth/LabyrinthGlyph2": {
    "name": "Inscrição de Bronze",
    "shortname": ""
  },
  "Metadata/NPC/Labyrinth/LabyrinthGlyph3": {
    "name": "Inscrição de Bronze",
    "shortname": ""
  },
  "Metadata/NPC/Labyrinth/LabyrinthGlyph4": {
    "name": "Inscrição de Bronze",
    "shortname": ""
  },
  "Metadata/NPC/Izaro": { "name": "Izaro", "shortname": "" },
  "Metadata/NPC/Labyrinth/WeylinGlyph1": { "name": "Poema", "shortname": "" },
  "Metadata/NPC/Labyrinth/WeylinGlyph2": { "name": "Poema", "shortname": "" },
  "Metadata/NPC/Labyrinth/WeylinGlyph3": { "name": "Poema", "shortname": "" },
  "Metadata/NPC/Labyrinth/WeylinGlyph4": { "name": "Poema", "shortname": "" },
  "Metadata/NPC/Labyrinth/WeylinGlyph5": { "name": "Poema", "shortname": "" },
  "Metadata/NPC/Info/MalachaiGlyphPrison": {
    "name": "Carta de Instruções",
    "shortname": ""
  },
  "Metadata/NPC/Info/MalachaiScrollGrainGate": {
    "name": "Ordens Oficiais",
    "shortname": ""
  },
  "Metadata/NPC/Info/MalachaiNoteDialla": {
    "name": "Nota do Diário",
    "shortname": ""
  },
  "Metadata/NPC/Info/MalachaiJournalLab": {
    "name": "Diário do Malachai",
    "shortname": ""
  },
  "Metadata/NPC/Info/MalachaiLetterSceptre": {
    "name": "Carta para Chitus",
    "shortname": ""
  },
  "Metadata/NPC/Rigwald": { "name": "Rigwald", "shortname": "" },
  "Metadata/NPC/Info/RigwaldGlyph1": { "name": "Inscrição", "shortname": "" },
  "Metadata/NPC/Info/RigwaldGlyph2": { "name": "Inscrição", "shortname": "" },
  "Metadata/NPC/Info/RigwaldGlyph3": { "name": "Inscrição", "shortname": "" },
  "Metadata/NPC/Info/RigwaldGlyph4": { "name": "Inscrição", "shortname": "" },
  "Metadata/NPC/Info/RigwaldGlyph5": { "name": "Inscrição", "shortname": "" },
  "Metadata/NPC/Info/RigwaldGlyph6": { "name": "Inscrição", "shortname": "" },
  "Metadata/NPC/League/Cadiro": {
    "name": "Cadiro Perandus",
    "shortname": "Cadiro"
  },
  "Metadata/NPC/League/Navali": { "name": "Navali", "shortname": "" },
  "Metadata/NPC/League/ProphecyDarkTome": {
    "name": "Tomo Sombrio",
    "shortname": ""
  },
  "Metadata/NPC/RigwaldMap": { "name": "O Rei Amaldiçoado", "shortname": "" },
  "Metadata/NPC/RigwaldMapSimplified": {
    "name": "Lycius, Uivo do Luar",
    "shortname": ""
  },
  "Metadata/NPC/League/NavaliWild": { "name": "Navali", "shortname": "" },
  "Metadata/NPC/League/NavaliHideout": { "name": "Navali", "shortname": "" },
  "Metadata/Monsters/Masters/Vaiko": {
    "name": "Balek Dawn",
    "shortname": "Balek"
  },
  "Metadata/NPC/League/Einhar": {
    "name": "Einhar Frey",
    "shortname": "Einhar"
  },
  "Metadata/NPC/League/EinharWild": {
    "name": "Einhar Frey",
    "shortname": "Einhar"
  },
  "Metadata/NPC/League/EinharMenagerie": {
    "name": "Einhar Frey",
    "shortname": "Einhar"
  },
  "Metadata/NPC/Epilogue/ZanaElderMid": {
    "name": "Zana, Mestre da Cartografia",
    "shortname": "Zana"
  },
  "Metadata/NPC/Epilogue/ZanaElder": {
    "name": "Zana, Mestre da Cartografia",
    "shortname": "Zana"
  },
  "Metadata/NPC/Epilogue/ZanaSecret": {
    "name": "Zana, Mestre da Cartografia",
    "shortname": "Zana"
  },
  "Metadata/NPC/Epilogue/ZanaShaper": {
    "name": "Zana, Mestre da Cartografia",
    "shortname": "Zana"
  },
  "Metadata/NPC/Shaper": { "name": "O Criador", "shortname": "" },
  "Metadata/NPC/Act5/Lani": { "name": "Lani", "shortname": "" },
  "Metadata/NPC/Act5/Vilenta": { "name": "Vilenta", "shortname": "" },
  "Metadata/NPC/Act5/Utula": { "name": "Utula", "shortname": "" },
  "Metadata/NPC/Act5/BannonTown": { "name": "Bannon", "shortname": "" },
  "Metadata/NPC/Act5/BannonInnocence": { "name": "Bannon", "shortname": "" },
  "Metadata/NPC/Act5/SinInnocence": { "name": "Sin", "shortname": "" },
  "Metadata/NPC/Act5/SinKitava": { "name": "Sin", "shortname": "" },
  "Metadata/NPC/Act5/Lilly": { "name": "Lilly Roth", "shortname": "Lilly" },
  "Metadata/NPC/Act6/Tarkleigh": { "name": "Tarkleigh", "shortname": "" },
  "Metadata/NPC/Act6/Bestel": { "name": "Bestel", "shortname": "" },
  "Metadata/NPC/Act6/Lilly": { "name": "Lilly Roth", "shortname": "Lilly" },
  "Metadata/NPC/Act6/WeylamBeacon": {
    "name": "Weylam Roth",
    "shortname": "Weylam"
  },
  "Metadata/NPC/Act6/WeylamReef1": {
    "name": "Weylam Roth",
    "shortname": "Weylam"
  },
  "Metadata/NPC/Act6/WeylamReef2": {
    "name": "Weylam Roth",
    "shortname": "Weylam"
  },
  "Metadata/NPC/Act6/SinTown": { "name": "Sin", "shortname": "" },
  "Metadata/NPC/Act6/SinTukohama": { "name": "Sin", "shortname": "" },
  "Metadata/NPC/Act6/SinAbberath": { "name": "Sin", "shortname": "" },
  "Metadata/NPC/Act6/SinShavronne": { "name": "Sin", "shortname": "" },
  "Metadata/NPC/Act6/SinRyslatha": { "name": "Sin", "shortname": "" },
  "Metadata/NPC/Act6/SinBrineKing": { "name": "Sin", "shortname": "" },
  "Metadata/NPC/Act6/NessaMudFlats": { "name": "Nessa", "shortname": "" },
  "Metadata/NPC/Act6/NessaPrisonersGate": { "name": "Nessa", "shortname": "" },
  "Metadata/NPC/Act6/NessaMerveilsCaverns": {
    "name": "Nessa",
    "shortname": ""
  },
  "Metadata/NPC/Act6/NessaBrineKing": { "name": "Nessa", "shortname": "" },
  "Metadata/NPC/League/NavaliMonkey": {
    "name": "Yama, o Branco",
    "shortname": ""
  },
  "Metadata/NPC/Act6/Tukohama": { "name": "Tukohama", "shortname": "" },
  "Metadata/NPC/Info/VaalLetters/VaalLetter_01": {
    "name": "Carta Vaal",
    "shortname": ""
  },
  "Metadata/NPC/Info/VaalLetters/VaalLetter_02": {
    "name": "Carta Vaal",
    "shortname": ""
  },
  "Metadata/NPC/Info/VaalLetters/VaalLetter_03": {
    "name": "Carta Vaal",
    "shortname": ""
  },
  "Metadata/NPC/Info/VaalLetters/VaalLetter_04": {
    "name": "Carta Vaal",
    "shortname": ""
  },
  "Metadata/NPC/Info/VaalLetters/VaalLetter_05": {
    "name": "Carta Vaal",
    "shortname": ""
  },
  "Metadata/NPC/Info/VaalLetters/VaalLetter_06": {
    "name": "Carta Vaal",
    "shortname": ""
  },
  "Metadata/NPC/Info/VaalLetters/VaalLetter_07": {
    "name": "Carta Vaal",
    "shortname": ""
  },
  "Metadata/NPC/Info/VaalLetters/VaalLetter_08": {
    "name": "Carta Vaal",
    "shortname": ""
  },
  "Metadata/NPC/Info/VaalLetters/VaalLetter_09": {
    "name": "Carta Vaal",
    "shortname": ""
  },
  "Metadata/NPC/Info/VaalLetters/VaalLetter_10": {
    "name": "Carta Vaal",
    "shortname": ""
  },
  "Metadata/NPC/Info/VaalLetters/VaalLetter_11": {
    "name": "Carta Vaal",
    "shortname": ""
  },
  "Metadata/NPC/Info/VaalLetters/VaalLetter_12": {
    "name": "Carta Vaal",
    "shortname": ""
  },
  "Metadata/NPC/Act7/SinTown": { "name": "Sin", "shortname": "" },
  "Metadata/NPC/Act7/SinRalakesh": { "name": "Sin", "shortname": "" },
  "Metadata/NPC/Act7/SinGruthkul": { "name": "Sin", "shortname": "" },
  "Metadata/NPC/Act7/SinArakaali": { "name": "Sin", "shortname": "" },
  "Metadata/NPC/Act7/SinMaligaro": { "name": "Sin", "shortname": "" },
  "Metadata/NPC/Act7/Weylam": { "name": "Weylam Roth", "shortname": "Weylam" },
  "Metadata/NPC/Act7/YeenaTown": { "name": "Yeena", "shortname": "" },
  "Metadata/NPC/Act7/YeenaVaalCity": { "name": "Yeena", "shortname": "" },
  "Metadata/NPC/Act7/Eramir": { "name": "Eramir", "shortname": "" },
  "Metadata/NPC/Act7/Helena": { "name": "Helena", "shortname": "" },
  "Metadata/NPC/Act7/SilkSins": { "name": "Silk", "shortname": "" },
  "Metadata/NPC/Act7/SilkArakaali": { "name": "Silk", "shortname": "" },
  "Metadata/NPC/Act8/Hargan": { "name": "Hargan", "shortname": "" },
  "Metadata/NPC/Act8/Maramoa": { "name": "Maramoa", "shortname": "" },
  "Metadata/NPC/Act8/ClarissaTown": { "name": "Clarissa", "shortname": "" },
  "Metadata/NPC/Act8/ClarissaQuay": { "name": "Clarissa", "shortname": "" },
  "Metadata/NPC/Act8/Tolman": { "name": "Tolman", "shortname": "" },
  "Metadata/NPC/Act8/SinTown": { "name": "Sin", "shortname": "" },
  "Metadata/NPC/Act8/SinDoedre": { "name": "Sin", "shortname": "" },
  "Metadata/NPC/Act8/SinYugul": { "name": "Sin", "shortname": "" },
  "Metadata/NPC/Act8/SinSolarisLunaris": { "name": "Sin", "shortname": "" },
  "Metadata/NPC/Act5/Avarius": { "name": "Avarius", "shortname": "" },
  "Metadata/NPC/Act5/Innocence": { "name": "Innocence", "shortname": "" },
  "Metadata/NPC/Info/RalakeshGlyph": {
    "name": "Ode para Ralakesh",
    "shortname": ""
  },
  "Metadata/NPC/Info/SilkLetter": { "name": "Carta de Amor", "shortname": "" },
  "Metadata/NPC/Info/MaligaroTome": {
    "name": "Manifesto de Maligaro",
    "shortname": ""
  },
  "Metadata/NPC/Info/ArakaaliGlyph1": {
    "name": "Altar para Arakaali",
    "shortname": ""
  },
  "Metadata/NPC/Info/ArakaaliGlyph2": {
    "name": "Altar para Arakaali",
    "shortname": ""
  },
  "Metadata/NPC/Info/ArakaaliGlyph3": {
    "name": "Altar para Arakaali",
    "shortname": ""
  },
  "Metadata/NPC/Info/ArakaaliGlyph4": {
    "name": "Altar para Arakaali",
    "shortname": ""
  },
  "Metadata/NPC/Info/ArakaaliGlyph5": {
    "name": "Altar para Arakaali",
    "shortname": ""
  },
  "Metadata/NPC/Info/UtulaGlyph1": {
    "name": "Fome de Kitava I",
    "shortname": ""
  },
  "Metadata/NPC/Info/UtulaGlyph2": {
    "name": "Fome de Kitava II",
    "shortname": ""
  },
  "Metadata/NPC/Info/UtulaGlyph3": {
    "name": "Fome de Kitava III",
    "shortname": ""
  },
  "Metadata/NPC/Info/DominusPrisonOrders": {
    "name": "Ordem da Proteção",
    "shortname": ""
  },
  "Metadata/NPC/Info/ShavronneManifesto": {
    "name": "Manifesto da Shavronne",
    "shortname": ""
  },
  "Metadata/NPC/Info/AbberathGlyph": {
    "name": "Escultura Primitiva",
    "shortname": ""
  },
  "Metadata/NPC/Info/RyslathaGlyph": {
    "name": "Escultura Desgastada",
    "shortname": ""
  },
  "Metadata/NPC/Info/TukohamaGlyph": {
    "name": "Escultura Karui",
    "shortname": ""
  },
  "Metadata/NPC/Info/BrineKingGlyph1": {
    "name": "Mensagem na Garrafa",
    "shortname": ""
  },
  "Metadata/NPC/Info/BrineKingGlyph2": {
    "name": "Diário de Bordo de Couro",
    "shortname": ""
  },
  "Metadata/NPC/Info/BrineKingGlyph3": {
    "name": "Fragmento da Carta",
    "shortname": ""
  },
  "Metadata/NPC/Info/BrineKingGlyph4": {
    "name": "Relatório Templário",
    "shortname": ""
  },
  "Metadata/NPC/Info/BrineKingGlyph5": {
    "name": "Altar ao Rei da Salmoura",
    "shortname": ""
  },
  "Metadata/NPC/Info/DoedreManifesto": {
    "name": "Manifesto de Doedre",
    "shortname": ""
  },
  "Metadata/NPC/Info/YugulGlyph": {
    "name": "Escultura Primitiva",
    "shortname": ""
  },
  "Metadata/NPC/Info/SolarisGlyph1": {
    "name": "Estátua de Solaris",
    "shortname": ""
  },
  "Metadata/NPC/Info/SolarisGlyph2": {
    "name": "Estátua de Solaris",
    "shortname": ""
  },
  "Metadata/NPC/Info/SolarisGlyph3": {
    "name": "Estátua de Solaris",
    "shortname": ""
  },
  "Metadata/NPC/Info/LunarisGlyph1": {
    "name": "Estátua de Lunaris",
    "shortname": ""
  },
  "Metadata/NPC/Info/LunarisGlyph2": {
    "name": "Estátua de Lunaris",
    "shortname": ""
  },
  "Metadata/NPC/Info/LunarisGlyph3": {
    "name": "Estátua de Lunaris",
    "shortname": ""
  },
  "Metadata/NPC/Info/VaalLetters/VaalLetter_13": {
    "name": "Diário de Pesquisa",
    "shortname": ""
  },
  "Metadata/NPC/Info/VaalLetters/VaalLetter_14": {
    "name": "Diário de Pesquisa",
    "shortname": ""
  },
  "Metadata/NPC/Info/VaalLetters/VaalLetter_15": {
    "name": "Diário de Pesquisa",
    "shortname": ""
  },
  "Metadata/NPC/Info/VaalLetters/VaalLetter_16": {
    "name": "Diário de Pesquisa",
    "shortname": ""
  },
  "Metadata/NPC/Info/TriumphOfInnocence": {
    "name": "Triunfo de Innocence",
    "shortname": ""
  },
  "Metadata/NPC/Info/StainedGlassWindow1": {
    "name": "Vitral",
    "shortname": ""
  },
  "Metadata/NPC/Info/StainedGlassWindow2": {
    "name": "Vitral",
    "shortname": ""
  },
  "Metadata/NPC/Info/StainedGlassWindow3": {
    "name": "Vitral",
    "shortname": ""
  },
  "Metadata/NPC/Info/StainedGlassWindow4": {
    "name": "Vitral",
    "shortname": ""
  },
  "Metadata/NPC/Info/StainedGlassWindow5": {
    "name": "Vitral",
    "shortname": ""
  },
  "Metadata/NPC/Info/StainedGlassWindow6": {
    "name": "Vitral",
    "shortname": ""
  },
  "Metadata/NPC/Info/StainedGlassWindow7": {
    "name": "Vitral",
    "shortname": ""
  },
  "Metadata/NPC/Info/StainedGlassWindow8": {
    "name": "Vitral",
    "shortname": ""
  },
  "Metadata/NPC/Act9/PetarusVanja": {
    "name": "Petarus e Vanja",
    "shortname": ""
  },
  "Metadata/NPC/Act9/Tasuni": { "name": "Tasuni", "shortname": "" },
  "Metadata/NPC/Act9/Irasha": { "name": "Irasha", "shortname": "" },
  "Metadata/NPC/Act9/SinTown": { "name": "Sin", "shortname": "" },
  "Metadata/NPC/Act9/SinQuarry": { "name": "Sin", "shortname": "" },
  "Metadata/NPC/Act9/SinGarukhan": { "name": "Sin", "shortname": "" },
  "Metadata/NPC/Act9/SinShakari": { "name": "Sin", "shortname": "" },
  "Metadata/NPC/Act9/SinCore": { "name": "Sin", "shortname": "" },
  "Metadata/NPC/Act9/Lilly": { "name": "Lilly Roth", "shortname": "Lilly" },
  "Metadata/NPC/Act9/Weylam": { "name": "Weylam Roth", "shortname": "Weylam" },
  "Metadata/NPC/Act10/Lani": { "name": "Lani", "shortname": "" },
  "Metadata/NPC/Act10/BannonTown": { "name": "Bannon", "shortname": "" },
  "Metadata/NPC/Act10/BannonRooftop": { "name": "Bannon", "shortname": "" },
  "Metadata/NPC/Act10/Lilly": { "name": "Lilly Roth", "shortname": "Lilly" },
  "Metadata/NPC/Act10/Weylam": { "name": "Weylam Roth", "shortname": "Weylam" },
  "Metadata/NPC/Act10/SinTown": { "name": "Sin", "shortname": "" },
  "Metadata/NPC/Act10/InnocenceTown": { "name": "Innocence", "shortname": "" },
  "Metadata/NPC/Act10/InnocenceSquare": {
    "name": "Innocence",
    "shortname": ""
  },
  "Metadata/NPC/Act10/SinTrough": { "name": "Sin", "shortname": "" },
  "Metadata/NPC/Act10/InnocenceTrough": {
    "name": "Innocence",
    "shortname": ""
  },
  "Metadata/NPC/Act5/SinOssuary": { "name": "Sin", "shortname": "" },
  "Metadata/NPC/Epilogue/Zana": {
    "name": "Zana, Mestre da Cartografia",
    "shortname": "Zana"
  },
  "Metadata/NPC/Missions/Wild/StrDexIntQuest": {
    "name": "Zana, Mestre da Cartografia",
    "shortname": "Zana"
  },
  "Metadata/NPC/Epilogue/Lani": { "name": "Lani", "shortname": "" },
  "Metadata/NPC/Epilogue/Weylam": {
    "name": "Weylam Roth",
    "shortname": "Weylam"
  },
  "Metadata/NPC/Epilogue/Lilly": { "name": "Lilly Roth", "shortname": "Lilly" },
  "Metadata/NPC/Epilogue/Sin": { "name": "Sin", "shortname": "" },
  "Metadata/NPC/Epilogue/Innocence": { "name": "Innocence", "shortname": "" },
  "Metadata/NPC/Act7/YeenaArakaali": { "name": "Yeena", "shortname": "" },
  "Metadata/NPC/Info/KitavaCultistGlyph1": {
    "name": "Trato Cultista",
    "shortname": ""
  },
  "Metadata/NPC/Info/KitavaCultistGlyph2": {
    "name": "Trato Cultista",
    "shortname": ""
  },
  "Metadata/NPC/Info/KitavaCultistGlyph3": {
    "name": "Trato Cultista",
    "shortname": ""
  },
  "Metadata/NPC/Info/ShaperMemoryFragmentBook": {
    "name": "Livro de Memórias",
    "shortname": ""
  },
  "Metadata/NPC/Info/ShaperFinalMemoryFragment": {
    "name": "Fragmento de Memória",
    "shortname": ""
  },
  "Metadata/Monsters/AtlasBosses/AtlasBossZana": {
    "name": "Zana, Mestre Cartógrafa",
    "shortname": "Zana"
  },
  "Metadata/Monsters/AtlasBosses/AtlasBossZanaElderUber": {
    "name": "Zana, Mestre Cartógrafa",
    "shortname": "Zana"
  },
  "Metadata/NPC/League/EinharCoast": {
    "name": "Einhar Frey",
    "shortname": "Einhar"
  },
  "Metadata/NPC/League/EinharMudFlats": {
    "name": "Einhar Frey",
    "shortname": "Einhar"
  },
  "Metadata/NPC/League/EinharPrisonersGate": {
    "name": "Einhar Frey",
    "shortname": "Einhar"
  },
  "Metadata/NPC/League/TreasureHunter": {
    "name": "Alva Valai",
    "shortname": "Alva"
  },
  "Metadata/NPC/League/TreasureHunterHideout": {
    "name": "Alva Valai",
    "shortname": "Alva"
  },
  "Metadata/Monsters/LeagueIncursion/Alva": {
    "name": "Alva Valai",
    "shortname": "Alva"
  }
}
