{
  "0": { "name": "Tarkleigh", "shortname": "" },
  "1": { "name": "Nessa", "shortname": "" },
  "2": { "name": "Bestel", "shortname": "" },
  "3": { "name": "Porteiro", "shortname": "" },
  "4": { "name": "Capitão Fairgraves", "shortname": "Fairgraves" },
  "5": { "name": "Exilado Moribundo", "shortname": "" },
  "6": { "name": "Brutus, o Carcereiro", "shortname": "Brutus" },
  "7": { "name": "Merveil", "shortname": "" },
  "8": { "name": "Eramir", "shortname": "" },
  "9": { "name": "Yeena", "shortname": "" },
  "10": { "name": "Greust", "shortname": "" },
  "11": { "name": "Silk", "shortname": "" },
  "12": { "name": "Alira", "shortname": "" },
  "13": { "name": "Kraityn", "shortname": "" },
  "14": { "name": "Oak", "shortname": "" },
  "15": { "name": "Hargan", "shortname": "" },
  "16": { "name": "Senhora Dialla", "shortname": "Dialla" },
  "17": { "name": "Senhora Dialla", "shortname": "Dialla" },
  "18": { "name": "Maramoa", "shortname": "" },
  "19": { "name": "Grigor", "shortname": "" },
  "20": { "name": "Clarissa", "shortname": "" },
  "21": { "name": "Clarissa", "shortname": "" },
  "22": { "name": "Diário de Shavronne", "shortname": "" },
  "23": { "name": "Helena", "shortname": "" },
  "24": { "name": "Helena", "shortname": "" },
  "25": { "name": "Siosa", "shortname": "" },
  "26": { "name": "Capitão Fairgraves", "shortname": "Fairgraves" },
  "27": { "name": "Piety", "shortname": "" },
  "28": { "name": "Gravicius", "shortname": "" },
  "29": { "name": "Dominus", "shortname": "" },
  "30": { "name": "Rei Kaom", "shortname": "Kaom" },
  "31": { "name": "Maligaro, o Inquisidor", "shortname": "Maligaro" },
  "32": { "name": "Shavronne", "shortname": "" },
  "33": { "name": "Malachai", "shortname": "" },
  "34": { "name": "Daresso", "shortname": "" },
  "35": { "name": "Oba", "shortname": "" },
  "36": { "name": "Carta de Arteri", "shortname": "" },
  "37": { "name": "Cartas de Exílio", "shortname": "" },
  "38": { "name": "Escultura Castigada", "shortname": "" },
  "39": { "name": "Escultura Castigada", "shortname": "" },
  "40": { "name": "Escultura Castigada", "shortname": "" },
  "41": { "name": "Escultura Castigada", "shortname": "" },
  "42": { "name": "Escultura Castigada", "shortname": "" },
  "43": { "name": "Escultura Castigada", "shortname": "" },
  "44": { "name": "Escultura Castigada", "shortname": "" },
  "45": { "name": "Pichação Antiga", "shortname": "" },
  "46": { "name": "Pichação Antiga", "shortname": "" },
  "47": { "name": "Pichação Antiga", "shortname": "" },
  "48": { "name": "Pichação Antiga", "shortname": "" },
  "49": { "name": "Pichação Antiga", "shortname": "" },
  "50": { "name": "Pichação Antiga", "shortname": "" },
  "51": { "name": "Caderno Antigo", "shortname": "" },
  "52": { "name": "Pele de Pescador", "shortname": "" },
  "53": { "name": "Diário Úmido", "shortname": "" },
  "54": { "name": "Herdeira", "shortname": "" },
  "55": { "name": "Dispositivo de Devaneio", "shortname": "" },
  "56": { "name": "Antigo Dispositivo de Devaneio", "shortname": "" },
  "57": { "name": "Dispositivo de Transmutação", "shortname": "" },
  "58": { "name": "As Crônicas da Pureza", "shortname": "" },
  "59": { "name": "As Crônicas da Pureza", "shortname": "" },
  "60": { "name": "As Crônicas da Pureza", "shortname": "" },
  "61": { "name": "As Crônicas da Pureza", "shortname": "" },
  "62": { "name": "As Crônicas da Pureza", "shortname": "" },
  "63": { "name": "As Crônicas da Pureza", "shortname": "" },
  "64": { "name": "Textos do Victario", "shortname": "" },
  "65": { "name": "Textos do Victario", "shortname": "" },
  "66": { "name": "Textos do Victario", "shortname": "" },
  "67": { "name": "Textos do Victario", "shortname": "" },
  "68": { "name": "Os Antigos", "shortname": "" },
  "69": { "name": "Os Antigos", "shortname": "" },
  "70": { "name": "Os Antigos", "shortname": "" },
  "71": { "name": "Os Antigos", "shortname": "" },
  "72": { "name": "Os Antigos", "shortname": "" },
  "73": { "name": "Os Antigos", "shortname": "" },
  "74": { "name": "Os Antigos", "shortname": "" },
  "75": { "name": "Placa", "shortname": "" },
  "76": { "name": "Gravuras na Madeira IV", "shortname": "" },
  "77": { "name": "Gravuras na Madeira III", "shortname": "" },
  "78": { "name": "Gravuras na Madeira I", "shortname": "" },
  "79": { "name": "Gravuras na Madeira II", "shortname": "" },
  "80": { "name": "Nota", "shortname": "" },
  "81": { "name": "Placa", "shortname": "" },
  "82": { "name": "Proclamação", "shortname": "" },
  "83": { "name": "Placa", "shortname": "" },
  "84": { "name": "Placa", "shortname": "" },
  "85": { "name": "Placa", "shortname": "" },
  "86": { "name": "Escultura Castigada", "shortname": "" },
  "87": { "name": "Escultura Castigada", "shortname": "" },
  "88": { "name": "Escultura Castigada", "shortname": "" },
  "89": { "name": "Escultura Castigada", "shortname": "" },
  "90": { "name": "Baú 1", "shortname": "" },
  "91": { "name": "Baú 2", "shortname": "" },
  "92": { "name": "Estandarte de Lioneye", "shortname": "" },
  "93": { "name": "Instruções do Ressonador", "shortname": "" },
  "94": { "name": "Confissão de Voll", "shortname": "" },
  "95": { "name": "Caderno de Malachai", "shortname": "" },
  "96": { "name": "Dedicação de Malachai", "shortname": "" },
  "97": { "name": "Kira", "shortname": "" },
  "98": { "name": "Oyun", "shortname": "" },
  "99": { "name": "Petarus e Vanja", "shortname": "" },
  "100": { "name": "Senhora Dialla", "shortname": "Dialla" },
  "101": { "name": "Senhora Dialla", "shortname": "Dialla" },
  "102": { "name": "Senhora Dialla", "shortname": "Dialla" },
  "103": { "name": "Dialla", "shortname": "Dialla" },
  "104": { "name": "Piety", "shortname": "Piety" },
  "105": { "name": "Piety", "shortname": "Piety" },
  "106": { "name": "Tasuni", "shortname": "" },
  "107": { "name": "Tora, Mestre da Caça", "shortname": "Tora" },
  "108": { "name": "Catarina, Mestre dos Mortos", "shortname": "Catarina" },
  "109": { "name": "Haku, Mestre das Armaduras", "shortname": "Haku" },
  "110": { "name": "Vorici, Mestre Assassino", "shortname": "Vorici" },
  "111": { "name": "Vagan, Mestre das Armas", "shortname": "Vagan" },
  "112": { "name": "Elreon, Mestre do Conhecimento", "shortname": "Elreon" },
  "113": { "name": "Zana, Mestre da Cartografia", "shortname": "Zana" },
  "114": { "name": "Leo, Mestre da Arena", "shortname": "Leo" },
  "115": { "name": "Tora, Mestre da Caça", "shortname": "Tora" },
  "116": { "name": "Catarina, Mestre dos Mortos", "shortname": "Catarina" },
  "117": { "name": "Haku, Mestre das Armaduras", "shortname": "Haku" },
  "118": { "name": "Vorici, Mestre Assassino", "shortname": "Vorici" },
  "119": { "name": "Vagan, Mestre das Armas", "shortname": "Vagan" },
  "120": { "name": "Elreon, Mestre do Conhecimento", "shortname": "Elreon" },
  "121": { "name": "Zana, Mestre da Cartografia", "shortname": "Zana" },
  "122": { "name": "Krillson, Mestre Pescador", "shortname": "Krillson" },
  "123": { "name": "Tora, Mestre da Caça", "shortname": "Tora" },
  "124": { "name": "Tora, Mestre da Caça", "shortname": "Tora" },
  "125": { "name": "Catarina, Mestre dos Mortos", "shortname": "Catarina" },
  "126": { "name": "Catarina, Mestre dos Mortos", "shortname": "Catarina" },
  "127": { "name": "Haku, Mestre das Armaduras", "shortname": "Haku" },
  "128": { "name": "Haku, Mestre das Armaduras", "shortname": "Haku" },
  "129": { "name": "Vorici, Mestre Assassino", "shortname": "Vorici" },
  "130": { "name": "Vorici, Mestre Assassino", "shortname": "Vorici" },
  "131": { "name": "Vagan, Mestre das Armas", "shortname": "Vagan" },
  "132": { "name": "Vagan, Mestre das Armas", "shortname": "Vagan" },
  "133": { "name": "Elreon, Mestre do Conhecimento", "shortname": "Elreon" },
  "134": { "name": "Elreon, Mestre do Conhecimento", "shortname": "Elreon" },
  "135": { "name": "Zana, Mestre da Cartografia", "shortname": "Zana" },
  "136": { "name": "Zana, Mestre da Cartografia", "shortname": "Zana" },
  "137": { "name": "Leo, Mestre da Arena", "shortname": "Leo" },
  "138": { "name": "Leo, Mestre da Arena", "shortname": "Leo" },
  "139": { "name": "Monografia de Bronze", "shortname": "" },
  "140": { "name": "Monografia de Bronze", "shortname": "" },
  "141": { "name": "Monografia de Bronze", "shortname": "" },
  "142": { "name": "Monografia de Bronze", "shortname": "" },
  "143": { "name": "Monografia de Bronze", "shortname": "" },
  "144": { "name": "Monografia de Bronze", "shortname": "" },
  "145": { "name": "Placa de Bronze", "shortname": "" },
  "146": { "name": "Inscrição de Bronze", "shortname": "" },
  "147": { "name": "Inscrição de Bronze", "shortname": "" },
  "148": { "name": "Inscrição de Bronze", "shortname": "" },
  "149": { "name": "Inscrição de Bronze", "shortname": "" },
  "150": { "name": "Izaro", "shortname": "" },
  "151": { "name": "Poema", "shortname": "" },
  "152": { "name": "Poema", "shortname": "" },
  "153": { "name": "Poema", "shortname": "" },
  "154": { "name": "Poema", "shortname": "" },
  "155": { "name": "Poema", "shortname": "" },
  "156": { "name": "Carta de Instruções", "shortname": "" },
  "157": { "name": "Ordens Oficiais", "shortname": "" },
  "158": { "name": "Nota do Diário", "shortname": "" },
  "159": { "name": "Diário do Malachai", "shortname": "" },
  "160": { "name": "Carta para Chitus", "shortname": "" },
  "161": { "name": "Rigwald", "shortname": "" },
  "162": { "name": "Inscrição", "shortname": "" },
  "163": { "name": "Inscrição", "shortname": "" },
  "164": { "name": "Inscrição", "shortname": "" },
  "165": { "name": "Inscrição", "shortname": "" },
  "166": { "name": "Inscrição", "shortname": "" },
  "167": { "name": "Inscrição", "shortname": "" },
  "168": { "name": "Cadiro Perandus", "shortname": "Cadiro" },
  "169": { "name": "Navali", "shortname": "" },
  "170": { "name": "Tomo Sombrio", "shortname": "" },
  "171": { "name": "O Rei Amaldiçoado", "shortname": "" },
  "172": { "name": "Lycius, Uivo do Luar", "shortname": "" },
  "173": { "name": "Navali", "shortname": "" },
  "174": { "name": "Navali", "shortname": "" },
  "175": { "name": "", "shortname": "" },
  "176": { "name": "", "shortname": "" },
  "177": { "name": "", "shortname": "" },
  "178": { "name": "", "shortname": "" },
  "179": { "name": "", "shortname": "" },
  "180": { "name": "", "shortname": "" },
  "181": { "name": "", "shortname": "" },
  "182": { "name": "O Criador", "shortname": "" },
  "183": { "name": "Zana, Mestre da Cartografia", "shortname": "Zana" },
  "184": { "name": "Lani", "shortname": "" },
  "185": { "name": "Vilenta", "shortname": "" },
  "186": { "name": "Utula", "shortname": "" },
  "187": { "name": "Bannon", "shortname": "" },
  "188": { "name": "Bannon", "shortname": "" },
  "189": { "name": "Sin", "shortname": "" },
  "190": { "name": "Sin", "shortname": "" },
  "191": { "name": "Lilly Roth", "shortname": "Lilly" },
  "192": { "name": "Tarkleigh", "shortname": "" },
  "193": { "name": "Bestel", "shortname": "" },
  "194": { "name": "Lilly Roth", "shortname": "Lilly" },
  "195": { "name": "Weylam Roth", "shortname": "Weylam" },
  "196": { "name": "Weylam Roth", "shortname": "Weylam" },
  "197": { "name": "Weylam Roth", "shortname": "Weylam" },
  "198": { "name": "Sin", "shortname": "" },
  "199": { "name": "Sin", "shortname": "" },
  "200": { "name": "Sin", "shortname": "" },
  "201": { "name": "Sin", "shortname": "" },
  "202": { "name": "Sin", "shortname": "" },
  "203": { "name": "Sin", "shortname": "" },
  "204": { "name": "Nessa", "shortname": "" },
  "205": { "name": "Nessa", "shortname": "" },
  "206": { "name": "Nessa", "shortname": "" },
  "207": { "name": "Nessa", "shortname": "" },
  "208": { "name": "Yama, o Branco", "shortname": "" },
  "209": { "name": "Tukohama", "shortname": "" },
  "210": { "name": "Carta Vaal", "shortname": "" },
  "211": { "name": "Carta Vaal", "shortname": "" },
  "212": { "name": "Carta Vaal", "shortname": "" },
  "213": { "name": "Carta Vaal", "shortname": "" },
  "214": { "name": "Carta Vaal", "shortname": "" },
  "215": { "name": "Carta Vaal", "shortname": "" },
  "216": { "name": "Carta Vaal", "shortname": "" },
  "217": { "name": "Carta Vaal", "shortname": "" },
  "218": { "name": "Carta Vaal", "shortname": "" },
  "219": { "name": "Carta Vaal", "shortname": "" },
  "220": { "name": "Carta Vaal", "shortname": "" },
  "221": { "name": "Carta Vaal", "shortname": "" },
  "222": { "name": "Sin", "shortname": "" },
  "223": { "name": "Sin", "shortname": "" },
  "224": { "name": "Sin", "shortname": "" },
  "225": { "name": "Sin", "shortname": "" },
  "226": { "name": "Sin", "shortname": "" },
  "227": { "name": "Weylam Roth", "shortname": "Weylam" },
  "228": { "name": "Yeena", "shortname": "" },
  "229": { "name": "Yeena", "shortname": "" },
  "230": { "name": "Eramir", "shortname": "" },
  "231": { "name": "Helena", "shortname": "" },
  "232": { "name": "Silk", "shortname": "" },
  "233": { "name": "Silk", "shortname": "" },
  "234": { "name": "Hargan", "shortname": "" },
  "235": { "name": "Maramoa", "shortname": "" },
  "236": { "name": "Clarissa", "shortname": "" },
  "237": { "name": "Clarissa", "shortname": "" },
  "238": { "name": "Tolman", "shortname": "" },
  "239": { "name": "Sin", "shortname": "" },
  "240": { "name": "Sin", "shortname": "" },
  "241": { "name": "Sin", "shortname": "" },
  "242": { "name": "Sin", "shortname": "" },
  "243": { "name": "Avarius", "shortname": "" },
  "244": { "name": "Inocência", "shortname": "" },
  "245": { "name": "Ode para Ralakesh", "shortname": "" },
  "246": { "name": "Carta de Amor", "shortname": "" },
  "247": { "name": "Manifesto de Maligaro", "shortname": "" },
  "248": { "name": "Altar para Arakaali", "shortname": "" },
  "249": { "name": "Altar para Arakaali", "shortname": "" },
  "250": { "name": "Altar para Arakaali", "shortname": "" },
  "251": { "name": "Altar para Arakaali", "shortname": "" },
  "252": { "name": "Altar para Arakaali", "shortname": "" },
  "253": { "name": "Fome de Kitava I", "shortname": "" },
  "254": { "name": "Fome de Kitava II", "shortname": "" },
  "255": { "name": "Fome de Kitava III", "shortname": "" },
  "256": { "name": "Ordem da Proteção", "shortname": "" },
  "257": { "name": "Manifesto da Shavronne", "shortname": "" },
  "258": { "name": "Escultura Primitiva", "shortname": "" },
  "259": { "name": "Escultura Desgastada", "shortname": "" },
  "260": { "name": "Escultura Karui", "shortname": "" },
  "261": { "name": "Mensagem na Garrafa", "shortname": "" },
  "262": { "name": "Diário de Bordo de Couro", "shortname": "" },
  "263": { "name": "Fragmento da Carta", "shortname": "" },
  "264": { "name": "Relatório Templário", "shortname": "" },
  "265": { "name": "Altar ao Rei da Salmoura", "shortname": "" },
  "266": { "name": "Manifesto de Doedre", "shortname": "" },
  "267": { "name": "Escultura Primitiva", "shortname": "" },
  "268": { "name": "Estátua de Solaris", "shortname": "" },
  "269": { "name": "Estátua de Solaris", "shortname": "" },
  "270": { "name": "Estátua de Solaris", "shortname": "" },
  "271": { "name": "Estátua de Lunaris", "shortname": "" },
  "272": { "name": "Estátua de Lunaris", "shortname": "" },
  "273": { "name": "Estátua de Lunaris", "shortname": "" },
  "274": { "name": "Diário de Pesquisa", "shortname": "" },
  "275": { "name": "Diário de Pesquisa", "shortname": "" },
  "276": { "name": "Diário de Pesquisa", "shortname": "" },
  "277": { "name": "Diário de Pesquisa", "shortname": "" },
  "278": { "name": "Triunfo da Inocência", "shortname": "" },
  "279": { "name": "Vitral", "shortname": "" },
  "280": { "name": "Vitral", "shortname": "" },
  "281": { "name": "Vitral", "shortname": "" },
  "282": { "name": "Vitral", "shortname": "" },
  "283": { "name": "Vitral", "shortname": "" },
  "284": { "name": "Vitral", "shortname": "" },
  "285": { "name": "Vitral", "shortname": "" },
  "286": { "name": "Vitral", "shortname": "" },
  "287": { "name": "Petarus e Vanja", "shortname": "" },
  "288": { "name": "Tasuni", "shortname": "" },
  "289": { "name": "Irasha", "shortname": "" },
  "290": { "name": "Sin", "shortname": "" },
  "291": { "name": "Sin", "shortname": "" },
  "292": { "name": "Sin", "shortname": "" },
  "293": { "name": "Sin", "shortname": "" },
  "294": { "name": "Sin", "shortname": "" },
  "295": { "name": "Lilly Roth", "shortname": "Lilly" },
  "296": { "name": "Weylam Roth", "shortname": "Weylam" },
  "297": { "name": "Lani", "shortname": "" },
  "298": { "name": "Bannon", "shortname": "" },
  "299": { "name": "Bannon", "shortname": "" },
  "300": { "name": "Lilly Roth", "shortname": "Lilly" },
  "301": { "name": "Weylam Roth", "shortname": "Weylam" },
  "302": { "name": "Sin", "shortname": "" },
  "303": { "name": "Inocência", "shortname": "" },
  "304": { "name": "Inocência", "shortname": "" },
  "305": { "name": "Sin", "shortname": "" },
  "306": { "name": "Inocência", "shortname": "" },
  "307": { "name": "Sin", "shortname": "" },
  "308": { "name": "Zana, Mestre da Cartografia", "shortname": "Zana" },
  "309": { "name": "Zana, Mestre da Cartografia", "shortname": "Zana" },
  "310": { "name": "Lani", "shortname": "" },
  "311": { "name": "Weylam Roth", "shortname": "Weylam" },
  "312": { "name": "Lilly Roth", "shortname": "Lilly" },
  "313": { "name": "Sin", "shortname": "" },
  "314": { "name": "Inocência", "shortname": "" },
  "315": { "name": "Yeena", "shortname": "" },
  "316": { "name": "Trato Cultista", "shortname": "" },
  "317": { "name": "Trato Cultista", "shortname": "" },
  "318": { "name": "Trato Cultista", "shortname": "" },
  "319": { "name": "Livro de Memórias", "shortname": "" }
}
