{
  "meta": {
    "include": "skill_stat_descriptions",
    "hasIdentifiers": false
  },
  "data": {
    "k": {
      "stats": ["skill_effect_duration_+%"],
      "translations": [
        {
          "matchers": [[1, "#"]],
          "text": "增加 %1%%% 持续时间 ",
          "formatters": []
        },
        {
          "matchers": [["#", -1]],
          "text": "减少 %1%%% 持续时间 ",
          "formatters": [
            {
              "id": "negate",
              "arg": 1
            }
          ]
        }
      ]
    }
  }
}
